Workbook

Sheet Dashboard
A1: MCAA — BLIGNAUTSRUS NORTH COMMUNITY ASSOCIATION
A2: Financial & Membership Dashboard | April 2026
A5: 📋 NAVIGATE TO TABS | B5: Tab Name | C5: Description
B6: Comprehensive list | C6: Master member database — all 533 entries including owner/tenant details, plot numbers, street addresses, debit order refs, and 13 months of payment history.
B7: Bank Statement Mar-26 | C7: Full April 2026 Capitec bank statement with every transaction categorised, matched to members, and flagged with confidence level.
B8: Reconciliation Mar-26 | C8: Month-end reconciliation summary — money in vs. money out, opening/closing balances, and per-member EFT & camera payment matching with differences.
B9: Expense Register | C9: Itemised list of all April 2026 outflows: salary, maintenance, camera purchase, utilities, bank fees, and reversals (R 36 792 total).
B10: Payment Summary | C10: Yearly membership payment overview — monthly collection totals (Apr 2025–Mar 2026), paying vs. non-paying member counts, and total revenue to date.
B11: Members Report | C11: Individual member payment detail report — total paid per member across the year, with non-payers highlighted in red.
B12: Matching Audit Log | C12: Full audit trail of every bank transaction matched to a member — method used (D/O batch, plot-street, name fuzzy), confidence level, and row reference.
B13: Street Captains | C13: Street captain directory — name, email, phone, and paying-member ratio per street (e.g. '4 of 8 paying on Blignaut Street').
B14: Blignautsrus North | C14: Plot-level master register for the Blignautsrus North area — owner/tenant, contacts, D/O reference, and full monthly payment columns.
B15: Notes | C15: Operational notes — Mercantile debit order system login instructions, Capitec support number, and useful reference links.
A17: 💰 MARCH 2026 FINANCIAL SNAPSHOT
B18: Money In (Mar) | D18: Money Out (Mar) | F18: Net (Mar) | H18: Closing Balance | J18: Recon Difference
B19: ='Bank Reconciliation'!D10 -> 60875 | D19: ='Bank Reconciliation'!D20 -> 36792 | F19: ='Bank Reconciliation'!D10-'Bank Reconciliation'!D20 -> 24083 | H19: ='Bank Reconciliation'!D27 -> 42267.9 | J19: ='Bank Reconciliation'!D28 -> -26
B20: DO + EFT + Camera | D20: Salary, maint., cameras, fees | F20: In minus Out | H20: Actual per bank statement | J20: Calculated vs Actual
A22: 📅 MONTHLY COLLECTIONS (Apr 2025 – Mar 2026) | H22: 👥 MEMBERSHIP STATS
B23: Month | C23: Collected (R) | D23: # Payers | E23: Avg / Payer (R) | H23: Metric | J23: Value
B24: 46137 | C24: ='Payment Summary'!C22 -> 26778 | D24: ='Payment Summary'!D22 -> 79 | E24: =IF(D24>0,C24/D24,0) -> 338.96203 | H24: Total Members on List | J24: ='Payment Summary'!D7 -> 533
B25: 46167 | C25: ='Payment Summary'!C23 -> 25841 | D25: ='Payment Summary'!D23 -> 78 | E25: =IF(D25>0,C25/D25,0) -> 331.29487 | H25: Paying Members | J25: ='Payment Summary'!D8 -> 132
B26: 46198 | C26: ='Payment Summary'!C24 -> 25108 | D26: ='Payment Summary'!D24 -> 74 | E26: =IF(D26>0,C26/D26,0) -> 339.2973 | H26: Non-Paying Members | J26: ='Payment Summary'!D9 -> 401
B27: 46228 | C27: ='Payment Summary'!C25 -> 24028 | D27: ='Payment Summary'!D25 -> 70 | E27: =IF(D27>0,C27/D27,0) -> 343.25714 | H27: Payment Rate | J27: ='Payment Summary'!D16 -> 0.25
B28: 46259 | C28: ='Payment Summary'!C26 -> 30233 | D28: ='Payment Summary'!D26 -> 71 | E28: =IF(D28>0,C28/D28,0) -> 425.8169 | H28: Unique Plot Numbers | J28: ='Payment Summary'!D11 -> 184
B29: 46290 | C29: ='Payment Summary'!C27 -> 26733 | D29: ='Payment Summary'!D27 -> 68 | E29: =IF(D29>0,C29/D29,0) -> 393.13235 | H29: Plots w/ Multiple Entries | J29: ='Payment Summary'!D12 -> 118
B30: 46320 | C30: ='Payment Summary'!C28 -> 24183 | D30: ='Payment Summary'!D28 -> 70 | E30: =IF(D30>0,C30/D30,0) -> 345.47143 | H30: Total Revenue (Year) | J30: ='Payment Summary'!D14 -> 372684
B31: 46351 | C31: ='Payment Summary'!C29 -> 21583 | D31: ='Payment Summary'!D29 -> 64 | E31: =IF(D31>0,C31/D31,0) -> 337.23438
B32: 46381 | C32: ='Payment Summary'!C30 -> 22883 | D32: ='Payment Summary'!D30 -> 66 | E32: =IF(D32>0,C32/D32,0) -> 346.71212
B33: 46048 | C33: ='Payment Summary'!C31 -> 24233 | D33: ='Payment Summary'!D31 -> 69 | E33: =IF(D33>0,C33/D33,0) -> 351.2029
B34: 46079 | C34: ='Payment Summary'!C32 -> 32833 | D34: ='Payment Summary'!D32 -> 66 | E34: =IF(D34>0,C34/D34,0) -> 497.4697
B35: Mar-26 (prev) | C35: ='Payment Summary'!C33 -> 27373 | D35: ='Payment Summary'!D33 -> 75 | E35: =IF(D35>0,C35/D35,0) -> 364.97333
B36: Mar-26 ★ | C36: ='Payment Summary'!C34 -> 60875 | D36: ='Payment Summary'!D34 -> 101 | E36: =IF(D36>0,C36/D36,0) -> 602.72277
B37: TOTAL | C37: ='Payment Summary'!D14 -> 372684
A41: 📄 MARCH 2026 EXPENSE BREAKDOWN | H41: 🏥 STREET CAPTAINS — COLLECTION RATE
B42: Category | C42: Amount (R) | D42: % of Total | E42: Notes | H42: Street | I42: Captain | J42: Paying | K42: of Total | L42: Rate
B43: ='Expense Register'!C2 -> Bank fee | C43: ='Expense Register'!D2 -> 414.98 | D43: =C43/'Expense Register'!D12 -> 0.011279082 | E43: ='Expense Register'!E2 -> DO service charge | H43: Blignaut Street | I43: (vacant) | J43: 4 | K43: 8 | L43: =J43/K43 -> 0.5
B44: ='Expense Register'!C3 -> Expense | C44: ='Expense Register'!D3 -> 4000 | D44: =C44/'Expense Register'!D12 -> 0.10871929 | E44: ='Expense Register'!E3 -> JLK MCAA | H44: De Wet Street | I44: Richard Bentheim | J44: 7 | K44: 17 | L44: =J44/K44 -> 0.41176471
B45: ='Expense Register'!C4 -> Utilities | C45: ='Expense Register'!D4 -> 471.51 | D45: =C45/'Expense Register'!D12 -> 0.012815558 | E45: ='Expense Register'!E4 -> Water — MR SN LANGA | H45: Eloff Street | I45: (vacant) | J45: 7 | K45: 19 | L45: =J45/K45 -> 0.36842105
B46: ='Expense Register'!C5 -> Reversal | C46: ='Expense Register'!D5 -> 200 | D46: =C46/'Expense Register'!D12 -> 0.0054359643 | E46: ='Expense Register'!E5 -> Unpaid DO reversal | H46: Eeufees Street | I46: Rolf | J46: 2 | K46: 11 | L46: =J46/K46 -> 0.18181818
B47: ='Expense Register'!C6 -> Salary | C47: ='Expense Register'!D6 -> 12500 | D47: =C47/'Expense Register'!D12 -> 0.33974777 | E47: ='Expense Register'!E6 -> Monthly salary — Mengo Sibanda | H47: Fifth Street | I47: Thulani Timile | J47: 5 | K47: 21 | L47: =J47/K47 -> 0.23809524
B48: ='Expense Register'!C7 -> Maintenance | C48: ='Expense Register'!D7 -> 3834 | D48: =C48/'Expense Register'!D12 -> 0.10420744 | E48: ='Expense Register'!E7 -> Fence repair — Luka | H48: First Avenue | I48: (vacant) | J48: 9 | K48: 30 | L48: =J48/K48 -> 0.3
B49: ='Expense Register'!C8 -> Reversal | C49: ='Expense Register'!D8 -> 350 | D49: =C49/'Expense Register'!D12 -> 0.0095129376 | E49: ='Expense Register'!E8 -> Unpaid DO reversal | H49: Golf Course Road | I49: Kevin | J49: 9 | K49: 26 | L49: =J49/K49 -> 0.34615385
B50: ='Expense Register'!C9 -> Utilities | C50: ='Expense Register'!D9 -> 471.51 | D50: =C50/'Expense Register'!D12 -> 0.012815558 | E50: ='Expense Register'!E9 -> Water — MR SN LANGA | H50: Green/Angle Road | I50: Mark Thompson | J50: 4 | K50: 14 | L50: =J50/K50 -> 0.28571429
B51: ='Expense Register'!C10 -> Camera purchase | C51: ='Expense Register'!D10 -> 14500 | D51: =C51/'Expense Register'!D12 -> 0.39410741 | E51: ='Expense Register'!E10 -> Camera equipment — Tary Design | H51: Hillside Road | I51: James Owens | J51: 5 | K51: 27 | L51: =J51/K51 -> 0.18518519
B52: ='Expense Register'!C11 -> Bank fee | C52: ='Expense Register'!D11 -> 50 | D52: =C52/'Expense Register'!D12 -> 0.0013589911 | E52: ='Expense Register'!E11 -> Monthly account fee | H52: Hugenote Street | I52: (vacant) | J52: 0 | K52: 12 | L52: =J52/K52 -> 0
B53: TOTAL | C53: ='Expense Register'!D12 -> 36792 | D53: 1 | H53: Nel Street | I53: Cliff Webb | J53: 4 | K53: 16 | L53: =J53/K53 -> 0.25
H54: Nico Pelser / 4th St. | I54: Paul Lottreaux | J54: 3 | K54: 26 | L54: =J54/K54 -> 0.11538462
H55: Orchard Road | I55: Anton | J55: 1 | K55: 19 | L55: =J55/K55 -> 0.052631579
H56: Third Ave. | I56: Chris Leeson | J56: 1 | K56: 14 | L56: =J56/K56 -> 0.071428571
H57: Second Avenue | I57: (vacant) | J57: 2 | K57: 18 | L57: =J57/K57 -> 0.11111111
H58: Road No 7 | I58: Zama Hlongwane | J58: 3 | K58: 17 | L58: =J58/K58 -> 0.17647059
H59: Voortrekker Street | I59: (vacant) | J59: 1 | K59: 13 | L59: =J59/K59 -> 0.076923077
H60: Road No 8 | I60: (vacant) | J60: 1 | K60: 5 | L60: =J60/K60 -> 0.2
A63: Dashboard auto-updates from source tabs. Last prepared: April 2026 | MCAA — Blignautsrus North Community Association

Sheet Comprehensive list
A1: Owner / Tenant | B1: Address | C1: D/O Ref | D1: Plot | E1: Contact 1 | F1: Contact 2 | G1: Contact 3 | H1: E-mail address | I1: Mar-25 DO | J1: Mar-25 EFT | K1: Apr-25 DO | L1: Apr-25 EFT | M1: May-25 DO | N1: May-25 EFT | O1: Jun-25 DO | P1: Jun-25 EFT | Q1: Jul-25 DO | R1: Jul-25 EFT | S1: Aug-25 DO | T1: Aug-25 EFT | U1: Sep-25 DO | V1: Sep-25 EFT | W1: Oct-25 DO | X1: Oct-25 EFT | Y1: Nov-25 DO | Z1: Nov-25 EFT | AA1: Dec-25 DO | AB1: Dec-25 EFT | AC1: Jan-26 DO | AD1: Jan-26 EFT | AE1: Feb-26 DO | AF1: Feb-26 EFT | AG1: Mar-26 DO | AH1: Mar-26 EFT | AI1: Apr-26 DO | AJ1: Apr-26 EFT | AK1: May-26 DO | AL1: May-26 EFT | AM1: Comments | AN1: Camera Payment
A2: Jason Batalides | B2: Blignaut Street | C2: HZB038 | D2: 1 | E2: 082 557 1110 | F2: 0614960119 | I2: 350 | K2: 350 | M2: 350 | O2: 350 | Q2: 350 | S2: 350 | U2: 350 | W2: 350 | Y2: 350 | AA2: 350 | AC2: 350 | AE2: 350 | AG2: 350 | AI2: 350 | AK2: 350 | AO2: 1
A3: Thom Khosa | B3: Hillside Road | D3: 1 | E3: 061 916 3908 | H3: thom.khosa@yahoo.com
A4: S.Potgieter | B4: Hillside Road | D4: 2 | E4: 084 579 0242 | H4: potgieter.steve@gmail.com
A5: Emmanual | B5: Hillside Road | D5: 2 | E5: 063 533 7777
A6: Sim Mdab | B6: Centre Road | D6: 3 | E6: 067 699 2598
A7: Thom Khosa? | B7: Hillside Road | D7: 3
A8: Graham and Alison Webster | B8: Hillside Road | C8: GLV 04 | D8: 4 | E8: 074 245 5446 | F8: 081 589 2689 | H8: grahamw@mweb.co.za | I8: 363 | K8: 363 | M8: 363 | O8: 363 | Q8: 363 | S8: 363 | U8: 363 | W8: 363 | Y8: 363 | AA8: 363 | AC8: 363 | AE8: 363 | AG8: 363 | AI8: 363 | AK8: 363 | AO8: 1
A9: Rowan De Viliers | B9: Hillside Road | D9: 4 | E9: 084 626 2755
A10: Dom Jacob | B10: Hillside Road | D10: 4 | E10: 074 245 5446
A11: John | B11: Hillside Road | D11: 5 | E11: 083 729 6349
A12: Karen | B12: Hillside Road | D12: 5 | E12: 083 575 4241
A13: Beverley Stevens-King | B13: Hillside Road | D13: 5 | E13: 068 150 0714 | F13: -
A14: Phumzile Bango | B14: Hillside Road | D14: 5 | E14: 073 221 5934 | H14: phumzile.bango81@gmail.com
A15: Nkosana Ngobese | B15: Hillside Road | D15: 5 | E15: 083 696 9618
A16: Sefore Pitso-Setere | B16: Hugenote Street | D16: 5 | E16: 076 766 6111 | H16: pitsosetere@yahoo.com
A17: Jonathan | B17: Main Street | D17: 5 | E17: 064 507 3761 | H17: jonathan@614.gmail.com
A18: VACANT | B18: Hillside Road | D18: 6
A19: Matthew | B19: Hillside Road | D19: 7 | E19: 062 896 7659
A20: Eugene | B20: Hugenote Street | D20: 7 | E20: 076 440 9248
A21: Desire (Girls on the Move) | B21: Blignaut Street | D21: 8 | E21: 011 490 0993 | H21: desire@girlsonthemove.co.za
A22: Sibosisu Kheswa | B22: Golf Course Road | D22: 8 | E22: 078 253 3008
A23: Robin Dryburgh | B23: Hillside Road | C23: ANNUAL EFT | D23: 8 | E23: 072 646 0512 | F23: 076 442 0330 | H23: robin@quosano.co.za | T23: 4000 | AM23: SIGNED - ANNUAL PAYMENT Aug25 | AO23: 1
A24: Miroslaw Benpkavic | B24: Danie Theron | C24: ANNUAL EFT | D24: 9 | E24: 082 452 1439 | H24: rupius@easywebmail.co.za | R24: 6000 | AH24: =6000+3500 -> 9500 | AM24: Cameras | AN24: 3500 | AO24: 1 | AP24: 3500
A25: Ian Long | B25: Blignaut Street | C25: BLG010 | D25: 10 | E25: 072 157 9623 | I25: 350 | K25: 350 | M25: 350 | O25: 350 | Q25: 350 | S25: 350 | U25: 350 | W25: 350 | Y25: 350 | AA25: 350 | AC25: 350 | AE25: 350 | AG25: 350 | AI25: 350 | AK25: 350 | AN25: 2000 | AO25: 1
A26: Heinrich Hendrikz | B26: Danie Theron | D26: 10 | E26: 081 016 2982 | H26: heinrichhendrikz@gmail.com | AH26: 500 | AM26: Cameras | AP26: 500
A27: Jabulusile Shandu | B27: Golf Course Road | C27: EFT | D27: 10 | E27: 083 302 0463 | H27: bavvmilesshandu@gmail.com
A28: Byron Canham | B28: Hillside Road | D28: 10 | E28: 078 610 8996 | H28: byroncanham67@gmail.com
A29: John Carr | B29: Blignaut Street | C29: EFT | D29: 11 | R29: 700 | T29: 350 | V29: 350 | X29: 350 | Z29: 350 | AB29: 350 | AD29: 350 | AF29: 350 | AH29: 350 | AJ29: 350 | AL29: 350 | AO29: 1
A30: VACANT | B30: Hillside Road | D30: 11
A31: Adams | B31: Hugenote Street | D31: 11 | E31: 072 908 9502
A32: Nkosinomusa Mpanza | B32: Blignaut Street | D32: 12 | E32: 083 775 1997 | H32: nkosinomusa.mpanza@gmail.com
A33: Russell Warden | B33: Danie Theron | D33: 12 | E33: 072 264 1626 | H33: russel@basixgroup.co.za
A34: Millicent | B34: Hillside Road | D34: 12 | E34: 060 335 7342 | H34: milly.makoti@yahoo.co.za
A35: Tshepo Makoti | B35: Hillside Road | D35: 12 | E35: 083 490 2586
A36: Jessica | B36: Hillside Road | D36: 12 | E36: 083 764 1855 | H36: sechabadaycare@gmail.com
A37: Lele Pedroncelli | B37: Danie Theron | D37: 13 | E37: 083 286 1327
A38: Fanie | B38: Hugenote Street | D38: 13 | E38: 063 088 3257 | H38: fanie@kieda.co.za
A39: Colin Blandford | B39: Blignaut Street | C39: BLG14 | D39: 14
A40: Patrick Mudhara | B40: Blignaut Street | D40: 14 | E40: 071 550 2414 | H40: patrickmudhara@gmailcom
A41: Thami Ndlovu | B41: Danie Theron | D41: 14 | E41: 076 030 1191 | H41: thamie.fiat.alfa@gmail.com
A42: Conrad | B42: Centre Road | D42: 15 | E42: 079 401 4231
A43: Ncedo Vilakazi | B43: Hugenote Street | D43: 15 | E43: 079 707 1993 | H43: vncedo@gmail.com
A44: Maureen Mhlongo | B44: Centre Road | C44: GLV016 | D44: 16 | E44: 083 442 0418 | H44: mawehmlongo@gmail.co.za | I44: 350 | K44: 350 | M44: 350 | O44: 350 | Q44: 350 | S44: 350 | U44: 350 | W44: 350 | Y44: 350 | AA44: 350 | AC44: 350 | AE44: 350 | AG44: 350 | AI44: 350 | AK44: 350 | AO44: 1
A45: Jeremy | B45: Centre Road | D45: 18 | E45: 076 125 5523
A46: Karel | B46: Hugenote Street | D46: 18 | E46: 082 308 1525 | H46: karel@kfb.co.za
A47: Pieter Fourie | B47: Fifth Street | C47: GLV019 | D47: 19 | E47: 083 444 6562 | H47: pieter@pfsourcing.co.za | I47: 350 | K47: 350 | M47: 350 | O47: 350 | Q47: 350 | S47: 350 | U47: 350 | W47: 350 | Y47: 350 | AA47: 350 | AC47: 350 | AE47: 350 | AG47: 350 | AH47: 1000 | AI47: 350 | AK47: 350 | AM47: Cameras | AO47: 1 | AP47: 1000
A48: Stephanie Fourie | B48: Fifth Street | D48: 19 | E48: 082 954 6078
A49: Andrew & Robyn Weeks | B49: Fifth Street | C49: GLV020 | D49: 20 | E49: 083 657 0409 | F49: 082 672 8198 | I49: 350 | K49: 350 | M49: 350 | O49: 350 | Q49: 350 | S49: 350 | U49: 350 | W49: 350 | Y49: 350 | AA49: 350 | AC49: 350 | AE49: 350 | AG49: 350 | AI49: 350 | AK49: 350 | AO49: 1
A50: Lune Weeks | B50: Fifth Street | D50: 20 | E50: 061 468 3671
A51: Angel Motloi | B51: Hugenote Street | D51: 20 | E51: 072 460 0685 | H51: motloiangie@gmail.com
A52: Minnie | B52: Hugenote Street | D52: 20 | E52: 082 796 7074 | H52: tinus@kwn.co.za
A53: E Nesbitt | B53: Fifth Street | D53: 21 | E53: 082 495 2879
A54: Abrahams | B54: Fifth Street | D54: 21 | E54: 082 643 0501
A55: Mariola Otomanska | B55: Fifth Street | D55: 21 | E55: 084 580 2849
A56: Brian | B56: Fifth Street | D56: 22 | E56: 082 460 2556
A57: Selway | B57: Fifth Street | D57: 22 | E57: 072 414 0513
A58: Rene | B58: First Avenue | D58: 22 | E58: 079 771 2258 | H58: ren-ab@hotmail.com
A59: Faith | B59: First Avenue | D59: 22 | E59: 083 382 0678 | H59: faith@tlc.org.za
A60: David Sibanda | B60: Hillside Road | D60: 22 | E60: 072 971 2467
A61: Sandile Mbanjwa | B61: Hugenote Street | C61: ANNUAL EFT | D61: 22 | AD61: 4200 | AM61: Annual payment 16/01/26 | AO61: 1
A62: Thembani Furumele | B62: Fifth Street | C62: EFT | D62: 23 | E62: 072 462 1924 | H62: thembanifurumele@gmail.com | AM62: Annual EFT pd Jul24
A63: Quintus | B63: First Avenue | D63: 23 | E63: 073 180 7977 | H63: tujays@net1.co.za
A64: Leon Janse Van Vuuren | B64: First Avenue | D64: 23 | E64: 082 507 8339
A65: K. Aboobaker | B65: Hugenote Street | D65: 24 | E65: 081 385 5048 | H65: mentorconch11@gmail.com
A66: Caid Schoeman | B66: Second Ave. | D66: 24 | E66: 072 916 8323 | H66: caidschoeman14@gmail.com
A67: Terence Du Preeze | B67: Second Ave. | D67: 24 | E67: 084 680 4046
A68: Kelvin Grobler | B68: Fifth Street | D68: 25 | E68: 082 589 8243
A69: Alan & Louise Proudfoot | B69: Fifth Street | C69: GLV025 | D69: 25 | E69: 083 653 3005 | F69: 083 776 1314 | H69: alan.c.proudfoot@gmail.com | I69: 385 | K69: 385 | M69: 385 | O69: 385 | Q69: 385 | S69: 385 | U69: 385 | W69: 385 | Y69: 385 | AA69: 385 | AC69: 385 | AE69: 385 | AG69: 385 | AI69: 385 | AK69: 385 | AO69: 1
A70: Angela Proudfoot | B70: Fifth Street | D70: 25
A71: Alex Klein | B71: Fifth Street | D71: 25 | E71: 081 040 0911
A72: May Lyna/ Judith | B72: First Avenue | C72: 1ST025 | D72: 25 | E72: 082 785 7572 | H72: lyna.v.may@gmail.com | AC72: 350 | AE72: 350 | AG72: 350 | AI72: 350 | AK72: 350 | AM72: Mar26 no funds | AO72: 1
A73: Chevis Coetzee | B73: Voortrekker St. | D73: 25 | E73: 084 458 5351 | H73: cheviscoetzee@gmail.com
A74: Derek | B74: Second Ave. | D74: 26 | E74: 079 244 2391
A75: Sonia Meysel | B75: Second Ave. | D75: 26 | E75: 073 772 1632
A76: Nina van der Walt | B76: Second Ave. | D76: 26 | E76: 064 019 2704
A77: Glenda | B77: Second Ave. | D77: 26 | E77: 082 558 8042 | H77: wendy@yoursoulpuzzle.co.za
A78: Ralf Meysel | B78: Second Ave. | D78: 26 | E78: 073 772 1632
A79: Riaan | B79: First Avenue | D79: 27 | E79: 082 498 2381 | H79: riaanlouw59@gmail.com
A80: Vusi & Lebogang Mojapelo | B80: Eloff Street | C80: EFT | D80: 28 | E80: 078 838 7331 | F80: 073 003 3996 | H80: lebogangmjp@gmail.com | AM80: NEW MEMBER TO PAY EFT
A81: Philip | B81: Eeufees Street | D81: 28 | E81: 083 519 4757
A82: Tshepang Mpitse | B82: Fifth Street | D82: 28 | E82: 076 358 2596 | H82: tshepangmpitse@gmail.com
A83: Clint Jardine | B83: Second Ave. | D83: 28 | E83: 083 229 8886 | H83: cjardine@joburgmarket.co.za
A84: Erika | B84: First Avenue | D84: 29 | E84: 084 045 8453
A85: Candice Smith | B85: Eloff Street | C85: EFT | D85: 30 | E85: 065 816 5033 | F85: 071 246 4529 | H85: candice1979@gmail.com | J85: 350 | L85: 350 | N85: 350 | P85: 350 | R85: 350 | T85: 350 | V85: 350 | X85: 350 | Z85: 350 | AB85: 350 | AD85: 350 | AF85: 350 | AH85: 350 | AJ85: 350 | AL85: 350 | AO85: 1
A86: Annushka Rooza | B86: Eloff Street | D86: 30 | E86: 084 997 8828 | H86: annushkarooza@gmail.com
A87: Rochelle Campbell | B87: Second Ave. | C87: 2ND030 | D87: 30 | E87: 072 077 9174 | K87: 350
A88: Shannon Davids | B88: Second Ave. | D88: 30 | E88: 083 319 7058 | H88: shannondavids8@gmail.com
A89: Neil Johnson | B89: Second Ave. | D89: 30 | E89: 076 422 6557
A90: Frank Duvenhage | B90: First Avenue | D90: 31 | E90: 073 151 5771 | H90: duvenhagefrank3@gmail.com
A91: Fred | B91: First Avenue | D91: 31 | E91: 084 556 2207
A92: John Hall | B92: First Avenue | D92: 31 | E92: 082 391 5145
A93: Haydrine Waveley | B93: Eloff Street | D93: 32 | E93: 083 246 8714 | H93: haydrine.waveley@santam.co.za
A94: Khanyisile Kama | B94: Eloff Street | D94: 32 | E94: 081 300 2739 | H94: khanyisilengwenya007@gmail.com
A95: Mel Nkosi | B95: Golf Course Road | C95: GOL032 | D95: 32 | E95: 071 427 2371 | H95: melnkosi72@gmail.com | AM95: SIGNED - NEW MEMBER MAR26
A96: Hugh and Charmaine Draai | B96: Fourth Street | C96: WLK033 | D96: 33 | E96: 082 296 9741 | H96: charmaindraai1@gmail.com | I96: 350 | K96: 350 | M96: 350 | O96: 350 | Q96: 350 | S96: 350 | U96: 350 | W96: 350 | Y96: 350 | AA96: 350 | AC96: 350 | AE96: 350 | AG96: 350 | AI96: 350 | AK96: 350 | AO96: 1
A97: Kim Baker | B97: Eloff Street | D97: 34 | E97: 083 321 4109 | H97: kimbaker43@gmail.com
A98: Thembisile Mazibuko | B98: Golf Course Road | D98: 34 | E98: 073 460 4665 | H98: themsileq@gmail.com | AB98: 200 | AF98: 170
A99: Lendl Preston | B99: First Avenue | D99: 35 | E99: 072 862 0652 | H99: lendlpreston@yahoo.com
A100: Anthony & Cameron Cox | B100: Fourth Street | D100: 35 | E100: 078 298 0061 | F100: 067 135 8156 | H100: cameron.edgesports@gmail.com
...

Sheet Bank Reconciliation
A1: MCAA — Bank Reconciliation | Capitec Business 1007012625
A3: March 2026 | 02 March – 31 March 2026
A4: Item | C4: Txns | D4: Amount (R)
A5: INCOME
A6: Membership — Debit Orders | C6: 14 | D6: 19625
A7: Membership — EFT (individual transfers) | C7: 45 | D7: 26750
A8: Camera payments — members | C8: 10 | D8: 11400
A9: Camera payments — sponsors | C9: 5 | D9: 3100
A10: TOTAL INCOME | D10: 60875
A12: EXPENSES
A13: Salary — Mengo Sibanda | C13: 1 | D13: 12500
A14: Maintenance — Fence repair (Luka) | C14: 1 | D14: 3834
A15: Camera purchase — Tary Design | C15: 1 | D15: 14500
A16: Utilities — Water MR SN LANGA (x2) | C16: 2 | D16: 943.02
A17: Other — JLK MCAA | C17: 1 | D17: 4000
A18: Bank fees & DO service charge | C18: 3 | D18: 464.98
A19: Reversals / Unpaid DOs (Weierings) | C19: 2 | D19: 550
A20: TOTAL EXPENSES | D20: 36792
A22: BALANCE CHECK
A23: Opening balance (01 Mar 2026) | D23: 18210.9
A24: + Total money in | D24: 60875
A25: − Total money out | D25: 36792
A26: Calculated closing balance | D26: 42293.9
A27: Actual closing balance (statement) | D27: 42267.9
A28: Difference (should = 0) | D28: -26
A30: Note: R26 difference — minor rounding across DO batch allocations. Under investigation.
A33: April 2026 | 01 April – 30 April 2026
A34: Item | C34: Txns | D34: Amount (R)
A35: INCOME
A36: Membership — Debit Orders (allocated) | C36: 12 | D36: 19625
A37: Membership — EFT (individual transfers) | C37: 18 | D37: 5180
A38: Camera payments — members | C38: 8 | D38: 8850
A39: Camera payments — sponsors | C39: 2 | D39: 1500
A40: DO batch actual received (unallocated R370) | D40: 19995
A41: TOTAL CREDITS | D41: 35525
A43: EXPENSES
A44: Bank fee — DO service charge (01/04) | C44: 1 | D44: 440.61
A45: Other — Red Hot Bit Consultants (02/04) | C45: 1 | D45: 3458
A46: Camera purchase — Tary Design (14/04) | C46: 1 | D46: 14502
A47: Reversal — Weierings Capitec (16/04) | C47: 1 | D47: 170
A48: Salary — Mengo Sibanda (27/04) | C48: 1 | D48: 12506
A49: Maintenance — Fence repair Luka (27/04) | C49: 1 | D49: 4756
A50: Reversal — Weierings Disc (29/04) | C50: 1 | D50: 350
A51: Bank fee — Monthly account fee (30/04) | C51: 1 | D51: 50
A52: TOTAL EXPENSES | D52: 36232.61
A54: BALANCE CHECK
A55: Opening balance (01 Apr 2026) | D55: 42267.9
A56: + Total credits | D56: 35525
A57: − Total expenses/debits | D57: 36232.61
A58: Calculated closing balance | D58: 41560.29
A59: Actual closing balance (statement) | D59: 41560.29
A60: Balance check | D60: PASS
A62: May 2026 | 01 May — 31 May 2026
A63: Item | C63: Txns | D63: Amount (R)
A64: INCOME
A65: Debit Order batch (MIDVILLECACONTRA) | C65: 14 | D65: 19805
A66: EFT — membership payments (matched) | C66: 19 | D66: 6710
A67: Camera — member contributions | C67: 4 | D67: 1860
A68: Camera — sponsors (rows 530-534) | C68: 1 | D68: 500
A69: EFT — unmatched (pending review) | C69: 3 | D69: 900
A70: EFT — reversed (G. van Jaarsveld 15/05, reversed 16/05) | C70: 1 | D70: 170
A71: TOTAL CREDITS | D71: 29945
A73: EXPENSES
A74: Utilities — Water/utilities – MR SN Langa (02/05/2026) | C74: 1 | D74: 574
A75: Bank fee — DO service charge – Capitec (04/05/2026) | C75: 1 | D75: 462.45
A76: Reversal — Unpaid DO reversal – R350 (member unknown, bounced at Standard Bank) (04/05/2026) | C76: 1 | D76: 350
A77: Camera purchase — Camera equipment – Tary Design (09/05/2026) | C77: 1 | D77: 16820.06
A78: Camera refund — Nel Street camera refund payment (09/05/2026) | C78: 1 | D78: 502
A79: Reversal — EFT reversal – G (16/05/2026) | C79: 1 | D79: 170
A80: Maintenance — Fence repair – Luka (25/05/2026) | C80: 1 | D80: 4752
A81: Salary — Monthly salary – Mengo Sibanda (25/05/2026) | C81: 1 | D81: 12502
A82: Bank fee — ATM cash deposit fees: R22 (29/05/2026) | C82: 1 | D82: 29.54
A83: Bank fee — Monthly account fee (31/05/2026) | C83: 1 | D83: 50
A84: TOTAL EXPENSES | D84: 36212.05
A86: BALANCE CHECK
A87: Opening balance (01 May 2026) | D87: 41560.29
A88: + Total credits | D88: 29945
A89: − Total expenses/debits | D89: 36212.05
A90: Calculated closing balance | D90: 35293.24
A91: Actual closing balance (statement) | D91: 35293.24
A92: Balance check | D92: PASS
A94: NOTES
A95: DO batch total (R19,805) vs Apr-26 DO schedule (R19,625) = +R180 discrepancy. One DO bounced (R350, WEIERINGS STANDARD, member unknown). Net DO collected R19,455.
A96: GERALDINE EVANS (x2, R400 total): member not found in Comprehensive list. Refer to administrator.
A97: ABSA BANK Joseph 98 (R500): partial name match only. Refer to administrator.
A98: G. van Jaarsveld (R170): EFT received 15/05, reversed 16/05 – NOT credited as payment for May.

Sheet Bank Statement
A1: MCAA — Bank Statement Register | Capitec Business 1007012625 | Mar–Apr 2026
A2: Month | B2: Date | C2: Reference | D2: Description | E2: Money In (R) | F2: Money Out (R) | G2: Fee (R) | H2: Balance (R) | I2: Category | J2: Matched Member | K2: Address / Plot | L2: D/O Type | M2: Notes
A3: March 2026 | Opening balance: R18,210.90
A4: Mar-26 | B4: 02/03/2026 | C4: MIDVILLECACONTRAEEC0936DA6573E | E4: 11103 | H4: 29313.9 | I4: Membership (DO batch) | J4: (DO batch)
A5: Mar-26 | B5: 02/03/2026 | C5: GOMES 116 DE WET | E5: 300 | H5: 29613.9 | I5: Membership (EFT) | J5: Phil & Chanty Gomes | K5: De Wet Street | Plot 116 | L5: EFT
A6: Mar-26 | B6: 02/03/2026 | C6: G.van Jaarsveld(87 Golf Course | E6: 170 | H6: 29783.9 | I6: Membership (EFT) | J6: Gareth van Jaarsveld | K6: Golf Course Road | Plot 87 | L6: GOL087-EFT
A7: Mar-26 | B7: 02/03/2026 | C7: 62 NICO PELSER STREE | E7: 200 | H7: 29983.9 | I7: Membership (EFT) | J7: Peggy Bennett | K7: Nico Pelser | Plot 62 | L7: EFT
A8: Mar-26 | B8: 02/03/2026 | C8: BLGN11F | E8: 350 | H8: 30333.9 | I8: Membership (EFT) | J8: John Carr | K8: Blignaut Street | Plot 11 | L8: EFT
A9: Mar-26 | B9: 02/03/2026 | C9: 37-1ST AVE WALKERVILLE | E9: 350 | H9: 30683.9 | I9: Membership (EFT) | J9: Peter Kairuz | K9: First Avenue | Plot 37 | L9: EFT
A10: Mar-26 | B10: 02/03/2026 | C10: CAPITEC B MCA1 03-26 | F10: 414.98 | H10: 30268.92 | I10: Bank fee | J10: Bank fee
A11: Mar-26 | B11: 03/03/2026 | C11: MIDVILLECACONTRAEAC49E66A6503A | E11: 800 | H11: 31068.92 | I11: Membership (DO batch) | J11: (DO batch)
A12: Mar-26 | B12: 03/03/2026 | C12: M MUTHALA | E12: 580 | H12: 31648.92 | I12: Membership (EFT) | J12: Gift & Charity Muthala | K12: Road No 7 | Plot 248/1 | L12: EFT
A13: Mar-26 | B13: 03/03/2026 | C13: 153 HOA HLONGWANE | E13: 300 | H13: 31948.92 | I13: Membership (EFT) | J13: Zama and Petunia Hlongwane | K13: Road No 7 | Plot 153 | L13: EFT
A14: Mar-26 | B14: 04/03/2026 | C14: JLK MCAA | F14: 4000 | G14: 6 | H14: 27942.92 | I14: Expense — RTC/other | J14: JLK MCAA
A15: Mar-26 | B15: 04/03/2026 | C15: MR SN LANGA MCAA Water | F15: 471.51 | G15: 1 | H15: 27470.41 | I15: Expense — Water | J15: MR SN LANGA MCAA Water
A16: Mar-26 | B16: 04/03/2026 | C16: M DE VRIES 148/1 | E16: 200 | H16: 27670.41 | I16: Membership (EFT) | J16: Johan and Lelly De Vries (Tennants) | K16: Road No 7 (No Name) | Plot 148/1 | L16: EFT
A17: Mar-26 | B17: 04/03/2026 | C17: 001 UNPAIDS/WEIERINGS CAPITEC | F17: 200 | H17: 27470.41 | I17: Reversal/Unpaid DO | J17: Reversal
A18: Mar-26 | B18: 05/03/2026 | C18: MIDVILLECACONTRAEDC59969A3513F | E18: 200 | H18: 27670.41 | I18: Membership (DO batch) | J18: (DO batch)
A19: Mar-26 | B19: 05/03/2026 | C19: 244RD7HAO-ANDRE | E19: 170 | H19: 27840.41 | I19: Membership (EFT) | J19: Andre De Vries | K19: Road No 7 | Plot 244 | L19: 244RD7HAO
A20: Mar-26 | B20: 05/03/2026 | C20: ABSA BANK 85 Golf Course Road | E20: 170 | H20: 28010.41 | I20: Membership (EFT) | J20: Previn Naidoo | K20: Golf Course Road | Plot 85 | L20: GOL085
A21: Mar-26 | B21: 05/03/2026 | C21: S GROENEWALD | E21: 200 | H21: 28210.41 | I21: Membership (EFT) | J21: Jason and Steven Groenewald | K21: Eeufees Street | Plot 69 | L21: EEU069
A22: Mar-26 | B22: 06/03/2026 | C22: MIDVILLECACONTRAEAC29A68A4503B | E22: 200 | H22: 28410.41 | I22: Membership (DO batch) | J22: (DO batch)
A23: Mar-26 | B23: 09/03/2026 | C23: MIDVILLECACONTRAE5C79F66AA5731 | E23: 363 | H23: 28773.41 | I23: Membership (DO batch) | J23: (DO batch)
A24: Mar-26 | B24: 12/03/2026 | C24: MIDVILLECACONTRAEFC19D69A55F38 | E24: 500 | H24: 29273.41 | I24: Membership (DO batch) | J24: (DO batch)
A25: Mar-26 | B25: 16/03/2026 | C25: MIDVILLECACONTRAEBC7936AAA5F3C | E25: 803 | H25: 30076.41 | I25: Membership (DO batch) | J25: (DO batch)
A26: Mar-26 | B26: 17/03/2026 | C26: MIDVILLECACONTRAEAC19B68A15F3C | E26: 363 | H26: 30439.41 | I26: Membership (DO batch) | J26: (DO batch)
A27: Mar-26 | B27: 18/03/2026 | C27: MIDVILLECACONTRAE4C69B6DA65431 | E27: 300 | H27: 30739.41 | I27: Membership (DO batch) | J27: (DO batch)
A28: Mar-26 | B28: 20/03/2026 | C28: ABSA BANK Plot82Blignautsrus | E28: 350 | H28: 31089.41 | I28: Membership (EFT) | J28: Terry Shapiro | K28: Danie Theron | Plot 82 | L28: ABSA BANK PLOT82BLIGNAUTSRUS
A29: Mar-26 | B29: 23/03/2026 | C29: MIDVILLECACONTRAE9C3986CA0543B | E29: 780 | H29: 31869.41 | I29: Membership (DO batch) | J29: (DO batch)
A30: Mar-26 | B30: 23/03/2026 | C30: 62 NICO PELSER ST. | E30: 3500 | H30: 35369.41 | I30: Membership (EFT) | J30: Peggy Bennett | K30: Nico Pelser | Plot 62 | L30: EFT
A31: Mar-26 | B31: 23/03/2026 | C31: DOLLY CAMERA | E31: 600 | H31: 35969.41 | I31: Camera | J31: Dolly Lolwane (Pride Elephant) | K31: Eloff Street | Plot 57 | L31: BLG057
A32: Mar-26 | B32: 24/03/2026 | C32: Sonya cameras 74 gol | E32: 500 | H32: 36469.41 | I32: Membership (EFT) | J32: Andy and Sonya Delahunty | K32: Golf Course Road | Plot 74 | L32: GOL074
A33: Mar-26 | B33: 24/03/2026 | C33: DAMASKUS PROJECTS | E33: 500 | H33: 36969.41 | I33: Camera (sponsor) | J33: DAMASKUS PROJECTS
A34: Mar-26 | B34: 24/03/2026 | C34: 94 NEL ST /CAMERAS | E34: 500 | H34: 37469.41 | I34: Membership (EFT) | J34: Debbie Rautenbach (Liesl Seymore) | K34: Nel Street | Plot 94 | L34: NEL094
A35: Mar-26 | B35: 24/03/2026 | C35: Bernadette sec camera 38 eloff | E35: 500 | H35: 37969.41 | I35: Camera | J35: Bunty & Lindsay Coryndon-Baker | K35: Eloff Street | Plot 38 | L35: ELO038
A36: Mar-26 | B36: 24/03/2026 | C36: 9 D. Theron; 2026 | E36: 6000 | H36: 43969.41 | I36: Membership (EFT) | J36: Miroslaw Benpkavic | K36: Danie Theron | Plot 9 | L36: ANNUAL EFT
A37: Mar-26 | B37: 24/03/2026 | C37: 9 D. Theron; CAMERA | E37: 3500 | H37: 47469.41 | I37: Camera | J37: Miroslaw Benpkavic | K37: Danie Theron | Plot 9 | L37: ANNUAL EFT
A38: Mar-26 | B38: 24/03/2026 | C38: FIFTH STREET - CAMER | E38: 1000 | H38: 48469.41 | I38: Camera (sponsor) | J38: FIFTH STREET - CAMER
A39: Mar-26 | B39: 25/03/2026 | C39: N SIBEKO | E39: 300 | H39: 48769.41 | I39: Membership (EFT) | J39: Nozisi (Nono) Sibeko & Given Sibeko | K39: Nico Pelser | Plot 58 | L39: NIC058
A40: Mar-26 | B40: 25/03/2026 | C40: MIDVILLECACONTRAE4CF996EAB533A | E40: 700 | H40: 49469.41 | I40: Membership (DO batch) | J40: (DO batch)
A41: Mar-26 | B41: 25/03/2026 | C41: William Cameras | E41: 500 | H41: 49969.41 | I41: Membership (EFT) | J41: William Jackson | K41: Eloff Street | Plot 55
A42: Mar-26 | B42: 25/03/2026 | C42: G THIELE | E42: 1500 | H42: 51469.41 | I42: Membership (EFT) | J42: Graham Thiele | K42: Nel Street | Plot 83 | L42: EFT
A43: Mar-26 | B43: 25/03/2026 | C43: Plot 100 Nel cameras | E43: 500 | H43: 51969.41 | I43: Camera | J43: Mbulelo Mbenenge | K43: Nel Street | Plot 100 | L43: PLOT 100 NEL CAMERAS
A44: Mar-26 | B44: 25/03/2026 | C44: P Fourie Cameras | E44: 1000 | H44: 52969.41 | I44: Membership (EFT) | J44: Pieter Fourie | K44: Fifth Street | Plot 19 | L44: GLV019
A45: Mar-26 | B45: 25/03/2026 | C45: Nathaniel/78 camera | E45: 2500 | H45: 55469.41 | I45: Camera | J45: Tracey Van Niekerk | K45: Nel Street | Plot 90 | L45: NEL090
A46: Mar-26 | B46: 25/03/2026 | C46: L CERQUEIRA - CAMERAS | E46: 500 | H46: 55969.41 | I46: Membership (EFT) | J46: Lore-lei Cerqueira | K46: Hillside Road | Plot 57
A47: Mar-26 | B47: 25/03/2026 | C47: Isobel Cameras Nel s | E47: 500 | H47: 56469.41 | I47: Membership (EFT) | J47: Isobel Van Der Motten | K47: Nel Street | Plot 92 | L47: NEL092
A48: Mar-26 | B48: 25/03/2026 | C48: 2ND 042 | E48: 200 | H48: 56669.41 | I48: Membership (EFT) | J48: Robert | K48: Second Ave. | Plot 42 | L48: 2ND 042
A49: Mar-26 | B49: 25/03/2026 | C49: KHUMBULA-CAMERAS | E49: 500 | H49: 57169.41 | I49: Membership (EFT) | J49: Khumbula Dlamini | K49: Orchard Road | Plot 100
A50: Mar-26 | B50: 25/03/2026 | C50: Pikkie 10 danie ther | E50: 500 | H50: 57669.41 | I50: Membership (EFT) | J50: Heinrich Hendrikz | K50: Danie Theron | Plot 10
A51: Mar-26 | B51: 25/03/2026 | C51: ABSA BANK 66 Nico P cameras | E51: 500 | H51: 58169.41 | I51: Membership (EFT) | J51: Bradley and Sharon Bantjes | K51: Nico Pelser | Plot 66 | L51: BLG 066
A52: Mar-26 | B52: 25/03/2026 | C52: ABSA BANK 82Blig terry+cameras | E52: 500 | H52: 58669.41 | I52: Membership (EFT) | J52: Terry Shapiro | K52: Danie Theron | Plot 82 | L52: ABSA BANK PLOT82BLIGNAUTSRUS
A53: Mar-26 | B53: 25/03/2026 | C53: SN MESSENGER | E53: 350 | H53: 59019.41 | I53: Membership (EFT) | J53: Steve Messenger/Juanita | K53: First Avenue | Plot 41 | L53: EFT
A54: Mar-26 | B54: 25/03/2026 | C54: Mpho Cameras | E54: 400 | H54: 59419.41 | I54: Membership (EFT) | J54: Mpho Thanjekwayo | K54: Eloff Street | Plot 45
A55: Mar-26 | B55: 26/03/2026 | C55: MIDVILLECACONTRAEDCE996EA7553A | E55: 1550 | H55: 60969.41 | I55: Membership (DO batch) | J55: (DO batch)
A56: Mar-26 | B56: 26/03/2026 | C56: 30 ELOFF STR. | E56: 350 | H56: 61319.41 | I56: Membership (EFT) | J56: Candice Smith | K56: Eloff Street | Plot 30 | L56: EFT
A57: Mar-26 | B57: 27/03/2026 | C57: MIDVILLECACONTRAE5CE9D6CA15431 | E57: 700 | H57: 62019.41 | I57: Membership (DO batch) | J57: (DO batch)
A58: Mar-26 | B58: 27/03/2026 | C58: Mengo Sibanda MCAA | F58: 12500 | G58: 6 | H58: 49513.41 | I58: Expense — Salary | J58: Salary — Mengo Sibanda
A59: Mar-26 | B59: 27/03/2026 | C59: LUKA MCAA FENCE | F59: 3834 | G59: 6 | H59: 45673.41 | I59: Expense — Maintenance | J59: Maintenance — fence repair
A60: Mar-26 | B60: 27/03/2026 | C60: ABSA BANK 85 Golf Course Road | E60: 170 | H60: 45843.41 | I60: Membership (EFT) | J60: Previn Naidoo | K60: Golf Course Road | Plot 85 | L60: GOL085
A61: Mar-26 | B61: 27/03/2026 | C61: ABSA BANK Previn-Cameras | E61: 500 | H61: 46343.41 | I61: Membership (EFT) | J61: Previn Naidoo | K61: Golf Course Road | Plot 85 | L61: GOL085
A62: Mar-26 | B62: 27/03/2026 | C62: S MASANGO 110 de Wet | E62: 350 | H62: 46693.41 | I62: Membership (EFT) | J62: Sifiso Masango / Tumiso | K62: De Wet Street | Plot 110 | L62: EFT
A63: Mar-26 | B63: 27/03/2026 | C63: Van Niekerk cameras | E63: 600 | H63: 47293.41 | I63: Camera (sponsor) | J63: Van Niekerk cameras
A64: Mar-26 | B64: 27/03/2026 | C64: Mark Thompson,37 Green rd,Golf | E64: 350 | H64: 47643.41 | I64: Membership (EFT) | J64: Mark Thompson | K64: Green Road | Plot 37 | L64: EFT
A65: Mar-26 | B65: 27/03/2026 | C65: Byron Nel st cameras | E65: 500 | H65: 48143.41 | I65: Camera (sponsor) | J65: Byron Nel st cameras
A66: Mar-26 | B66: 27/03/2026 | C66: AF BANK chapman nel str cam | E66: 1000 | H66: 49143.41 | I66: Camera | J66: Andrew Chapman | K66: Nel Street | Plot 96
A67: Mar-26 | B67: 27/03/2026 | C67: 43 FIRST AVENUE CAMERAS | E67: 500 | H67: 49643.41 | I67: Membership (EFT) | J67: Shaun Traut | K67: First Avenue | Plot 43 | L67: 1ST043
A68: Mar-26 | B68: 27/03/2026 | C68: PayShapReceived BLGN15F | E68: 500 | H68: 50143.41 | I68: Camera (sponsor) | J68: PayShapReceived BLGN15F
A69: Mar-26 | B69: 27/03/2026 | C69: BLG108 | E69: 200 | H69: 50343.41 | I69: Membership (EFT) | J69: Nazam | K69: De Wet Street | Plot 108 | L69: EFT REF 108 BLG, BLG108, BLG108 CAMERA
A70: Mar-26 | B70: 27/03/2026 | C70: 65 NICO PELSER | E70: 500 | H70: 50843.41 | I70: Membership (EFT) | J70: Reginald Kairuz and Lucielle De Klerk | K70: Nico Pelser | Plot 65 | L70: NIC065
A71: Mar-26 | B71: 28/03/2026 | C71: MIDVILLECACONTRAE5C59A6AA55530 | E71: 1263 | H71: 52106.41 | I71: Membership (DO batch) | J71: (DO batch)
A72: Mar-26 | B72: 28/03/2026 | C72: ABSA BANK Khanyile Cameras 46E | E72: 500 | H72: 52606.41 | I72: Membership (EFT) | J72: Thulani Khanyile | K72: Eeufees Street | Plot 46 | L72: HAR046
A73: Mar-26 | B73: 28/03/2026 | C73: ABSA BANK philip 70 nel camera | E73: 1000 | H73: 53606.41 | I73: Camera | J73: Philip Kruis | K73: Nel Street | Plot 70
A74: Mar-26 | B74: 28/03/2026 | C74: 88 Nel Camera From 1053405588 | E74: 500 | H74: 54106.41 | I74: Camera | J74: K Bland | K74: Nel Street | Plot 88
A75: Mar-26 | B75: 28/03/2026 | C75: E KEARTLAND CAMERA | E75: 500 | H75: 54606.41 | I75: Camera | J75: Evelyn Keartland | K75: De Wet Street | Plot 91 | L75: BLG091
A76: Mar-26 | B76: 28/03/2026 | C76: BLG108 CAMERA | E76: 300 | H76: 54906.41 | I76: Camera | J76: Nazam | K76: De Wet Street | Plot 108 | L76: EFT REF 108 BLG, BLG108, BLG108 CAMERA
A77: Mar-26 | B77: 28/03/2026 | C77: 001 UNPAIDS/WEIERINGS DISC | F77: 350 | H77: 54556.41 | I77: Reversal/Unpaid DO | J77: Reversal
A78: Mar-26 | B78: 29/03/2026 | C78: MR SN LANGA MCAA Water | F78: 471.51 | G78: 1 | H78: 54083.9 | I78: Expense — Water | J78: MR SN LANGA MCAA Water
A79: Mar-26 | B79: 30/03/2026 | C79: GOMES 116 DE WET | E79: 300 | H79: 54383.9 | I79: Membership (EFT) | J79: Phil & Chanty Gomes | K79: De Wet Street | Plot 116 | L79: EFT
A80: Mar-26 | B80: 30/03/2026 | C80: 153 HOA HLONGWANE | E80: 300 | H80: 54683.9 | I80: Membership (EFT) | J80: Zama and Petunia Hlongwane | K80: Road No 7 | Plot 153 | L80: EFT
A81: Mar-26 | B81: 30/03/2026 | C81: ABSA BANK John Potter Cameras | E81: 600 | H81: 55283.9 | I81: Membership (EFT) | J81: John & Karin Potter (Benches Direct) | K81: Eloff Street | Plot 59 | L81: ELO059
A82: Mar-26 | B82: 30/03/2026 | C82: 39 Green road | E82: 400 | H82: 55683.9 | I82: Membership (EFT) | J82: Belinda Groenewald | K82: Green Road | Plot 39 | L82: EFT
A83: Mar-26 | B83: 30/03/2026 | C83: 39 Green road Camera | E83: 500 | H83: 56183.9 | I83: Camera | J83: Belinda Groenewald | K83: Green Road | Plot 39 | L83: EFT
A84: Mar-26 | B84: 30/03/2026 | C84: TARY DESIGN MCAA | F84: 14500 | G84: 6 | H84: 41677.9 | I84: Expense — Camera purchase | J84: Camera purchase — Tary Design
A85: Mar-26 | B85: 30/03/2026 | C85: 77 SHORT ROAD POTGIE | E85: 170 | H85: 41847.9 | I85: Membership (EFT) | J85: Petrus Johannes Potgieter (Ronnie) | K85: Short Road | Plot 77 | L85: EFT
A86: Mar-26 | B86: 30/03/2026 | C86: 79 GOLF COURSE CA WRIGHT | E86: 300 | H86: 42147.9 | I86: Membership (EFT) | J86: Carlo & Shoneez Wright | K86: Golf Course Road | Plot 79 | L86: EFT
A87: Mar-26 | B87: 31/03/2026 | C87: 244RD7HAO-ANDRE | E87: 170 | H87: 42317.9 | I87: Membership (EFT) | J87: Andre De Vries | K87: Road No 7 | Plot 244 | L87: 244RD7HAO
A88: Mar-26 | B88: 31/03/2026 | C88: Month S/Fee | F88: 50 | H88: 42267.9 | I88: Bank fee | J88: Bank fee
A89: Subtotals — March 2026 | E89: 60875 | F89: 36792 | G89: 26
A91: April 2026 | Opening balance: R42,267.90
A92: Apr-26 | B92: 01/04/2026 | C92: MIDVILLECACONTRAEAC59369A3513C | D92: Inward EFT Credit | E92: 11153 | H92: 53420.9 | I92: Membership (DO batch) | L92: DO | M92: Capitec DO batch — distributed to D/O members
A93: Apr-26 | B93: 01/04/2026 | C93: Ndlovu:60 Fifth ST | D93: Retail Cr Transfer | E93: 350 | H93: 53770.9 | I93: Membership (EFT) | J93: Sonya Herbst | L93: EFT | M93: Multiple plot matches: [229, 230, 231]
A94: Apr-26 | B94: 01/04/2026 | C94: CAPITEC B MCA1 04-26 | D94: Debit Order | F94: 440.61 | H94: 53330.29 | I94: Expense | M94: DO service charge
A95: Apr-26 | B95: 02/04/2026 | C95: MIDVILLECACONTRAEEC49367AA503E | D95: Inward EFT Credit | E95: 350 | H95: 53680.29 | I95: Membership (DO batch) | L95: DO | M95: Capitec DO batch — distributed to D/O members
A96: Apr-26 | B96: 02/04/2026 | C96: Red Hot Bit Consultants MCAA To 62847482669 | D96: Outward EFT | F96: 3456 | G96: 2 | H96: 50222.29 | I96: Expense | M96: Unclassified outgoing
A97: Apr-26 | B97: 02/04/2026 | C97: BLGN11F | D97: Inward EFT Credit | E97: 350 | H97: 50572.29 | I97: Membership (EFT) | J97: John Carr | L97: EFT | M97: Resolved: John Carr, Blignaut, plot 11
A98: Apr-26 | B98: 02/04/2026 | C98: FIFTH STREET - CAMER | D98: Inward EFT Credit | E98: 1000 | H98: 51572.29 | I98: Camera (sponsor) | J98: Fifth Street | L98: Camera | M98: Standalone camera sponsor: Fifth Street
A99: Apr-26 | B99: 02/04/2026 | C99: 62 NICO PELSER ST. | D99: Inward EFT Credit | E99: 200 | H99: 51772.29 | I99: Membership (EFT) | J99: Sheldon Schostar | L99: EFT | M99: Multiple plot matches: [242, 243, 244]
A100: Apr-26 | B100: 02/04/2026 | C100: M.THOMPSON,GREEN RD,CAMERAS | D100: Inward EFT Credit | E100: 500 | H100: 52272.29 | I100: Camera | J100: Mark Thompson | L100: Camera | M100: M. Thompson, Green Rd — Camera
A101: Apr-26 | B101: 04/04/2026 | C101: MIDVILLECACONTRAE8C59A6DA25E31 | D101: Inward EFT Credit | E101: 600 | H101: 52872.29 | I101: Membership (DO batch) | L101: DO | M101: Capitec DO batch — distributed to D/O members
...

Sheet Matching Audit Log
A1: Date | B1: Reference | C1: Amount In (R) | D1: Category | E1: Method | F1: Confidence | G1: Matched Member | H1: Row # | I1: Address | J1: Plot | K1: Notes
A2: 02/03/2026 | B2: MIDVILLECACONTRAEEC0936DA6573E | C2: 11103 | D2: Membership (DO batch) | E2: DO_BATCH | F2: HIGH | G2: (DO batch)
A3: 02/03/2026 | B3: GOMES 116 DE WET | C3: 300 | D3: Membership (EFT) | E3: PLOT_STREET | F3: HIGH | G3: Phil & Chanty Gomes | H3: 411 | I3: De Wet Street | J3: 116
A4: 02/03/2026 | B4: G.van Jaarsveld(87 Golf Course | C4: 170 | D4: Membership (EFT) | E4: PLOT_STREET | F4: HIGH | G4: Gareth van Jaarsveld | H4: 341 | I4: Golf Course Road | J4: 87
A5: 02/03/2026 | B5: 62 NICO PELSER STREE | C5: 200 | D5: Membership (EFT) | E5: PLOT_STREET | F5: HIGH | G5: Peggy Bennett | H5: 243 | I5: Nico Pelser | J5: 62
A6: 02/03/2026 | B6: BLGN11F | C6: 350 | D6: Membership (EFT) | E6: MANUAL | F6: HIGH | G6: John Carr | H6: 29 | I6: Blignaut Street | J6: 11 | K6: Matched via Blignaut St plot 11 (John Carr) — D/O ref updated
A7: 02/03/2026 | B7: 37-1ST AVE WALKERVILLE | C7: 350 | D7: Membership (EFT) | E7: MANUAL | F7: HIGH | G7: Peter Kairuz | H7: 106 | I7: First Avenue | J7: 37 | K7: Matched via 1st Ave plot 37 — Peter Kairuz
A8: 03/03/2026 | B8: MIDVILLECACONTRAEAC49E66A6503A | C8: 800 | D8: Membership (DO batch) | E8: DO_BATCH | F8: HIGH | G8: (DO batch)
A9: 03/03/2026 | B9: M MUTHALA | C9: 580 | D9: Membership (EFT) | E9: NAME | F9: HIGH | G9: Gift & Charity Muthala | H9: 494 | I9: Road No 7 | J9: 248/1
A10: 03/03/2026 | B10: 153 HOA HLONGWANE | C10: 300 | D10: Membership (EFT) | E10: PLOT_ONLY | F10: HIGH | G10: Zama and Petunia Hlongwane | H10: 433 | I10: Road No 7 | J10: 153
A11: 04/03/2026 | B11: M DE VRIES 148/1 | C11: 200 | D11: Membership (EFT) | E11: PLOT_ONLY | F11: HIGH | G11: Johan and Lelly De Vries (Tennants) | H11: 485 | I11: Road No 7 (No Name) | J11: 148/1
A12: 05/03/2026 | B12: MIDVILLECACONTRAEDC59969A3513F | C12: 200 | D12: Membership (DO batch) | E12: DO_BATCH | F12: HIGH | G12: (DO batch)
A13: 05/03/2026 | B13: 244RD7HAO-ANDRE | C13: 170 | D13: Membership (EFT) | E13: NAME | F13: HIGH | G13: Andre De Vries | H13: 443 | I13: Road No 7 | J13: 244
A14: 05/03/2026 | B14: ABSA BANK 85 Golf Course Road | C14: 170 | D14: Membership (EFT) | E14: PLOT_STREET | F14: HIGH | G14: Previn Naidoo | H14: 335 | I14: Golf Course Road | J14: 85
A15: 05/03/2026 | B15: S GROENEWALD | C15: 200 | D15: Membership (EFT) | E15: NAME | F15: HIGH | G15: Jason and Steven Groenewald | H15: 268 | I15: Eeufees Street | J15: 69
A16: 06/03/2026 | B16: MIDVILLECACONTRAEAC29A68A4503B | C16: 200 | D16: Membership (DO batch) | E16: DO_BATCH | F16: HIGH | G16: (DO batch)
A17: 09/03/2026 | B17: MIDVILLECACONTRAE5C79F66AA5731 | C17: 363 | D17: Membership (DO batch) | E17: DO_BATCH | F17: HIGH | G17: (DO batch)
A18: 12/03/2026 | B18: MIDVILLECACONTRAEFC19D69A55F38 | C18: 500 | D18: Membership (DO batch) | E18: DO_BATCH | F18: HIGH | G18: (DO batch)
A19: 16/03/2026 | B19: MIDVILLECACONTRAEBC7936AAA5F3C | C19: 803 | D19: Membership (DO batch) | E19: DO_BATCH | F19: HIGH | G19: (DO batch)
A20: 17/03/2026 | B20: MIDVILLECACONTRAEAC19B68A15F3C | C20: 363 | D20: Membership (DO batch) | E20: DO_BATCH | F20: HIGH | G20: (DO batch)
A21: 18/03/2026 | B21: MIDVILLECACONTRAE4C69B6DA65431 | C21: 300 | D21: Membership (DO batch) | E21: DO_BATCH | F21: HIGH | G21: (DO batch)
A22: 20/03/2026 | B22: ABSA BANK Plot82Blignautsrus | C22: 350 | D22: Membership (EFT) | E22: REF_EXACT | F22: HIGH | G22: Terry Shapiro | H22: 323 | I22: Danie Theron | J22: 82
A23: 23/03/2026 | B23: MIDVILLECACONTRAE9C3986CA0543B | C23: 780 | D23: Membership (DO batch) | E23: DO_BATCH | F23: HIGH | G23: (DO batch)
A24: 23/03/2026 | B24: 62 NICO PELSER ST. | C24: 3500 | D24: Membership (EFT) | E24: PLOT_STREET | F24: HIGH | G24: Peggy Bennett | H24: 243 | I24: Nico Pelser | J24: 62
A25: 23/03/2026 | B25: DOLLY CAMERA | C25: 600 | D25: Camera | E25: NAME | F25: HIGH | G25: Dolly Lolwane (Pride Elephant) | H25: 516 | I25: Eloff Street | J25: 57
A26: 24/03/2026 | B26: Sonya cameras 74 gol | C26: 500 | D26: Membership (EFT) | E26: NAME | F26: HIGH | G26: Andy and Sonya Delahunty | H26: 291 | I26: Golf Course Road | J26: 74
A27: 24/03/2026 | B27: DAMASKUS PROJECTS | C27: 500 | D27: Camera (sponsor) | E27: SPONSOR | F27: HIGH | G27: DAMASKUS PROJECTS
A28: 24/03/2026 | B28: 94 NEL ST /CAMERAS | C28: 500 | D28: Membership (EFT) | E28: PLOT_STREET | F28: HIGH | G28: Debbie Rautenbach (Liesl Seymore) | H28: 360 | I28: Nel Street | J28: 94
A29: 24/03/2026 | B29: Bernadette sec camera 38 eloff | C29: 500 | D29: Camera | E29: PLOT_STREET | F29: HIGH | G29: Bunty & Lindsay Coryndon-Baker | H29: 112 | I29: Eloff Street | J29: 38
A30: 24/03/2026 | B30: 9 D. Theron; 2026 | C30: 6000 | D30: Membership (EFT) | E30: PLOT_ONLY | F30: HIGH | G30: Miroslaw Benpkavic | H30: 24 | I30: Danie Theron | J30: 9
A31: 24/03/2026 | B31: 9 D. Theron; CAMERA | C31: 3500 | D31: Camera | E31: PLOT_ONLY | F31: HIGH | G31: Miroslaw Benpkavic | H31: 24 | I31: Danie Theron | J31: 9
A32: 24/03/2026 | B32: FIFTH STREET - CAMER | C32: 1000 | D32: Camera (sponsor) | E32: SPONSOR | F32: HIGH | G32: FIFTH STREET - CAMER
A33: 25/03/2026 | B33: N SIBEKO | C33: 300 | D33: Membership (EFT) | E33: NAME | F33: HIGH | G33: Nozisi (Nono) Sibeko & Given Sibeko | H33: 222 | I33: Nico Pelser | J33: 58
A34: 25/03/2026 | B34: MIDVILLECACONTRAE4CF996EAB533A | C34: 700 | D34: Membership (DO batch) | E34: DO_BATCH | F34: HIGH | G34: (DO batch)
A35: 25/03/2026 | B35: William Cameras | C35: 500 | D35: Membership (EFT) | E35: NAME | F35: HIGH | G35: William Jackson | H35: 515 | I35: Eloff Street | J35: 55
A36: 25/03/2026 | B36: G THIELE | C36: 1500 | D36: Membership (EFT) | E36: NAME | F36: HIGH | G36: Graham Thiele | H36: 329 | I36: Nel Street | J36: 83
A37: 25/03/2026 | B37: Plot 100 Nel cameras | C37: 500 | D37: Camera | E37: REF_EXACT | F37: HIGH | G37: Mbulelo Mbenenge | H37: 379 | I37: Nel Street | J37: 100 | K37: D/O ref "Plot 100 Nel cameras" → Mbulelo Mbenenge (row 379)
A38: 25/03/2026 | B38: P Fourie Cameras | C38: 1000 | D38: Membership (EFT) | E38: NAME | F38: HIGH | G38: Pieter Fourie | H38: 47 | I38: Fifth Street | J38: 19
A39: 25/03/2026 | B39: Nathaniel/78 camera | C39: 2500 | D39: Camera | E39: MANUAL | F39: HIGH | G39: Tracey Van Niekerk | H39: 348 | I39: Nel Street | J39: 90
A40: 25/03/2026 | B40: L CERQUEIRA - CAMERAS | C40: 500 | D40: Membership (EFT) | E40: NAME | F40: HIGH | G40: Lore-lei Cerqueira | H40: 217 | I40: Hillside Road | J40: 57
A41: 25/03/2026 | B41: Isobel Cameras Nel s | C41: 500 | D41: Membership (EFT) | E41: NAME | F41: HIGH | G41: Isobel Van Der Motten | H41: 353 | I41: Nel Street | J41: 92
A42: 25/03/2026 | B42: 2ND 042 | C42: 200 | D42: Membership (EFT) | E42: REF_EXACT | F42: HIGH | G42: Robert | H42: 138 | I42: Second Ave. | J42: 42 | K42: D/O ref 2ND 042 → Robert, Second Ave plot 42 (row 138)
A43: 25/03/2026 | B43: KHUMBULA-CAMERAS | C43: 500 | D43: Membership (EFT) | E43: NAME | F43: HIGH | G43: Khumbula Dlamini | H43: 381 | I43: Orchard Road | J43: 100
A44: 25/03/2026 | B44: Pikkie 10 danie ther | C44: 500 | D44: Membership (EFT) | E44: PLOT_STREET | F44: HIGH | G44: Heinrich Hendrikz | H44: 26 | I44: Danie Theron | J44: 10
A45: 25/03/2026 | B45: ABSA BANK 66 Nico P cameras | C45: 500 | D45: Membership (EFT) | E45: PLOT_STREET | F45: HIGH | G45: Bradley and Sharon Bantjes | H45: 260 | I45: Nico Pelser | J45: 66
A46: 25/03/2026 | B46: ABSA BANK 82Blig terry+cameras | C46: 500 | D46: Membership (EFT) | E46: MANUAL | F46: HIGH | G46: Terry Shapiro | H46: 323 | I46: Danie Theron | J46: 82
A47: 25/03/2026 | B47: SN MESSENGER | C47: 350 | D47: Membership (EFT) | E47: NAME | F47: HIGH | G47: Steve Messenger/Juanita | H47: 128 | I47: First Avenue | J47: 41
A48: 25/03/2026 | B48: Mpho Cameras | C48: 400 | D48: Membership (EFT) | E48: NAME | F48: HIGH | G48: Mpho Thanjekwayo | H48: 144 | I48: Eloff Street | J48: 45
A49: 26/03/2026 | B49: MIDVILLECACONTRAEDCE996EA7553A | C49: 1550 | D49: Membership (DO batch) | E49: DO_BATCH | F49: HIGH | G49: (DO batch)
A50: 26/03/2026 | B50: 30 ELOFF STR. | C50: 350 | D50: Membership (EFT) | E50: PLOT_STREET | F50: HIGH | G50: Candice Smith | H50: 85 | I50: Eloff Street | J50: 30
A51: 27/03/2026 | B51: MIDVILLECACONTRAE5CE9D6CA15431 | C51: 700 | D51: Membership (DO batch) | E51: DO_BATCH | F51: HIGH | G51: (DO batch)
A52: 27/03/2026 | B52: ABSA BANK 85 Golf Course Road | C52: 170 | D52: Membership (EFT) | E52: PLOT_STREET | F52: HIGH | G52: Previn Naidoo | H52: 335 | I52: Golf Course Road | J52: 85
A53: 27/03/2026 | B53: ABSA BANK Previn-Cameras | C53: 500 | D53: Membership (EFT) | E53: NAME | F53: HIGH | G53: Previn Naidoo | H53: 335 | I53: Golf Course Road | J53: 85
A54: 27/03/2026 | B54: S MASANGO 110 de Wet | C54: 350 | D54: Membership (EFT) | E54: PLOT_STREET | F54: HIGH | G54: Sifiso Masango / Tumiso | H54: 399 | I54: De Wet Street | J54: 110
A55: 27/03/2026 | B55: Van Niekerk cameras | C55: 600 | D55: Camera (sponsor) | E55: SPONSOR | F55: HIGH | G55: Van Niekerk cameras
A56: 27/03/2026 | B56: Mark Thompson,37 Green rd,Golf | C56: 350 | D56: Membership (EFT) | E56: PLOT_STREET | F56: HIGH | G56: Mark Thompson | H56: 109 | I56: Green Road | J56: 37
A57: 27/03/2026 | B57: Byron Nel st cameras | C57: 500 | D57: Camera (sponsor) | E57: SPONSOR | F57: HIGH | G57: Byron Nel st cameras
A58: 27/03/2026 | B58: AF BANK chapman nel str cam | C58: 1000 | D58: Camera | E58: NAME | F58: HIGH | G58: Andrew Chapman | H58: 367 | I58: Nel Street | J58: 96
A59: 27/03/2026 | B59: 43 FIRST AVENUE CAMERAS | C59: 500 | D59: Membership (EFT) | E59: PLOT_STREET | F59: HIGH | G59: Shaun Traut | H59: 140 | I59: First Avenue | J59: 43
A60: 27/03/2026 | B60: PayShapReceived BLGN15F | C60: 500 | D60: Camera (sponsor) | E60: SPONSOR | F60: HIGH | G60: PayShapReceived BLGN15F
A61: 27/03/2026 | B61: BLG108 | C61: 200 | D61: Membership (EFT) | E61: REF_EXACT | F61: HIGH | G61: Nazam | H61: 396 | I61: De Wet Street | J61: 108 | K61: Multi-ref: EFT REF 108 BLG, BLG108, BLG108 CAMERA → Nazam (row 396)
A62: 27/03/2026 | B62: 65 NICO PELSER | C62: 500 | D62: Membership (EFT) | E62: PLOT_STREET | F62: HIGH | G62: Reginald Kairuz and Lucielle De Klerk | H62: 254 | I62: Nico Pelser | J62: 65
A63: 28/03/2026 | B63: MIDVILLECACONTRAE5C59A6AA55530 | C63: 1263 | D63: Membership (DO batch) | E63: DO_BATCH | F63: HIGH | G63: (DO batch)
A64: 28/03/2026 | B64: ABSA BANK Khanyile Cameras 46E | C64: 500 | D64: Membership (EFT) | E64: NAME | F64: HIGH | G64: Thulani Khanyile | H64: 146 | I64: Eeufees Street | J64: 46
A65: 28/03/2026 | B65: ABSA BANK philip 70 nel camera | C65: 1000 | D65: Camera | E65: PLOT_STREET | F65: HIGH | G65: Philip Kruis | H65: 280 | I65: Nel Street | J65: 70
A66: 28/03/2026 | B66: 88 Nel Camera From 1053405588 | C66: 500 | D66: Camera | E66: PLOT_STREET | F66: HIGH | G66: K Bland | H66: 342 | I66: Nel Street | J66: 88
A67: 28/03/2026 | B67: E KEARTLAND CAMERA | C67: 500 | D67: Camera | E67: NAME | F67: HIGH | G67: Evelyn Keartland | H67: 351 | I67: De Wet Street | J67: 91
A68: 28/03/2026 | B68: BLG108 CAMERA | C68: 300 | D68: Camera | E68: REF_EXACT | F68: HIGH | G68: Nazam | H68: 396 | I68: De Wet Street | J68: 108 | K68: Multi-ref: EFT REF 108 BLG, BLG108, BLG108 CAMERA → Nazam (row 396)
A69: 30/03/2026 | B69: GOMES 116 DE WET | C69: 300 | D69: Membership (EFT) | E69: PLOT_STREET | F69: HIGH | G69: Phil & Chanty Gomes | H69: 411 | I69: De Wet Street | J69: 116
A70: 30/03/2026 | B70: 153 HOA HLONGWANE | C70: 300 | D70: Membership (EFT) | E70: PLOT_ONLY | F70: HIGH | G70: Zama and Petunia Hlongwane | H70: 433 | I70: Road No 7 | J70: 153
A71: 30/03/2026 | B71: ABSA BANK John Potter Cameras | C71: 600 | D71: Membership (EFT) | E71: NAME | F71: HIGH | G71: John & Karin Potter (Benches Direct) | H71: 223 | I71: Eloff Street | J71: 59
A72: 30/03/2026 | B72: 39 Green road | C72: 400 | D72: Membership (EFT) | E72: PLOT_STREET | F72: HIGH | G72: Belinda Groenewald | H72: 117 | I72: Green Road | J72: 39
A73: 30/03/2026 | B73: 39 Green road Camera | C73: 500 | D73: Camera | E73: PLOT_STREET | F73: HIGH | G73: Belinda Groenewald | H73: 117 | I73: Green Road | J73: 39
A74: 30/03/2026 | B74: 77 SHORT ROAD POTGIE | C74: 170 | D74: Membership (EFT) | E74: PLOT_STREET | F74: HIGH | G74: Petrus Johannes Potgieter (Ronnie) | H74: 308 | I74: Short Road | J74: 77
A75: 30/03/2026 | B75: 79 GOLF COURSE CA WRIGHT | C75: 300 | D75: Membership (EFT) | E75: PLOT_STREET | F75: HIGH | G75: Carlo & Shoneez Wright | H75: 311 | I75: Golf Course Road | J75: 79
A76: 31/03/2026 | B76: 244RD7HAO-ANDRE | C76: 170 | D76: Membership (EFT) | E76: NAME | F76: HIGH | G76: Andre De Vries | H76: 443 | I76: Road No 7 | J76: 244
A77: 01/04/2026 | B77: Ndlovu:60 Fifth ST | C77: 350 | D77: Membership (EFT) | E77: MATCHED | F77: MED | G77: Sonya Herbst | H77: 229 | I77: Fifth Street | K77: Multiple plot matches: [229, 230, 231]
A78: 02/04/2026 | B78: BLGN11F | C78: 350 | D78: Membership (EFT) | E78: REF_EXACT | F78: HIGH | G78: John Carr | H78: 29 | I78: Blignaut Street | K78: Resolved: John Carr, Blignaut, plot 11
A79: 02/04/2026 | B79: 62 NICO PELSER ST. | C79: 200 | D79: Membership (EFT) | E79: MATCHED | F79: MED | G79: Sheldon Schostar | H79: 242 | I79: Golf Course Road | K79: Multiple plot matches: [242, 243, 244]
A80: 02/04/2026 | B80: M.THOMPSON,GREEN RD,CAMERAS | C80: 500 | D80: Camera | E80: MATCHED | F80: HIGH | G80: Mark Thompson | H80: 109 | I80: Green Road | K80: M. Thompson, Green Rd — Camera
A81: 04/04/2026 | B81: S GROENEWALD | C81: 200 | D81: Membership (EFT) | E81: MATCHED | F81: HIGH | G81: Jason and Steven Groenewald | H81: 268 | I81: Eeufees Street | K81: EEU069 — Steven Groenewald, Eeufees, plot 69
A82: 04/04/2026 | B82: PayShapReceived J O'shea- Cameras | C82: 500 | D82: Camera | E82: MATCHED | F82: MED | G82: Richard Shearer | H82: 126 | I82: Second Ave. | K82: J O'Shea camera payment
A83: 07/04/2026 | B83: M DE VRIES 148/1 | C83: 200 | D83: Membership (EFT) | E83: REF_EXACT | F83: HIGH | G83: Johan and Lelly De Vries (Tennants) | H83: 485 | I83: Road No 7 (No Name) | K83: Resolved: Madelena De Vries, plot 148/1
A84: 07/04/2026 | B84: 37-1ST AVE WALKERVILLE | C84: 350 | D84: Membership (EFT) | E84: REF_EXACT | F84: HIGH | G84: Peter Kairuz | H84: 106 | I84: First Avenue | K84: Resolved: Peter Kairuz, First Ave, plot 37
A85: 08/04/2026 | B85: Camera-40 2nd Ave.-R Shearer | C85: 1000 | D85: Camera | E85: MATCHED | F85: MED | G85: Bonfale Muchono | H85: 121 | I85: De Wet Street | K85: Multiple plot matches: [121, 122, 123, 124, 125, 126, 127]
A86: 09/04/2026 | B86: J OWENS CAMERA GOLFC | C86: 500 | D86: Camera | E86: MATCHED | F86: MED | G86: James Owens | H86: 230 | I86: Golf Course Road | K86: Single name match
A87: 09/04/2026 | B87: PLOT 42 BLG | C87: 170 | D87: Membership (EFT) | E87: MATCHED | F87: MED | G87: Greg and Paula Peters | H87: 131 | I87: Eloff Street | K87: Multiple plot matches: [131, 132, 133, 134, 135, 136, 137, 138, 510]
A88: 15/04/2026 | B88: G.van Jaarsveld(87 Golf Course | C88: 170 | D88: Membership (EFT) | E88: MATCHED | F88: HIGH | G88: Gareth van Jaarsveld | H88: 341 | I88: Golf Course Road | K88: GOL087-EFT — Gareth van Jaarsveld
... A102: 30/04/2026 | B102: Mark Thompson,37 Green rd,Golf | C102: 350 | D102: Membership (EFT) | E102: MATCHED | F102: MED | G102: Tom Pearson | H102: 105 | I102: Eloff Street | K102: Multiple plot matches: [105, 106, 107, 108, 109, 110, 111]
A103: 02/05/2026 | B103: 62 NICO PELSER ST. | C103: 200 | D103: Membership (EFT) | E103: MATCHED | F103: HIGH | G103: Peggy Bennett | H103: 243 | I103: Nico Pelser
A104: 02/05/2026 | B104: S GROENEWALD | C104: 200 | D104: Membership (EFT) | E104: MATCHED | F104: HIGH | G104: Jason and Steven Groenewald | H104: 268 | I104: Eeufees Street
A105: 02/05/2026 | B105: 79 GOLF COURSE CA WRIGHT | C105: 300 | D105: Membership (EFT) | E105: MATCHED | F105: HIGH | G105: Carlo & Shoneez Wright | H105: 311 | I105: Golf Course Road
A106: 04/05/2026 | B106: 37-1ST AVE WALKERVILLE | C106: 350 | D106: Membership (EFT) | E106: MATCHED | F106: HIGH | G106: Peter Kairuz | H106: 106 | I106: First Avenue
A107: 04/05/2026 | B107: BLGN11F | C107: 350 | D107: Membership (EFT) | E107: MATCHED | F107: HIGH | G107: John Carr | H107: 29 | I107: Blignaut Street
A108: 05/05/2026 | B108: 244RD7HAO-ANDRE | C108: 170 | D108: Membership (EFT) | E108: MATCHED | F108: HIGH | G108: Andre De Vries | H108: 443 | I108: Road No 7
A109: 07/05/2026 | B109: ABSA BANK 82Blig terry+cameras | C109: 350 | D109: Camera | E109: MATCHED | F109: HIGH | G109: Terry Shapiro | H109: 323 | I109: Danie Theron
A110: 08/05/2026 | B110: 54 nico pelser | C110: 1600 | D110: Membership (EFT) | E110: MATCHED | F110: HIGH | G110: Richard and Pumla Mashele | H110: 205 | I110: Nico Pelser
A111: 08/05/2026 | B111: M DE VRIES 148/1 | C111: 200 | D111: Membership (EFT) | E111: MATCHED | F111: HIGH | G111: Johan and Lelly De Vries (Tennants) | H111: 485 | I111: Road No 7
A112: 25/05/2026 | B112: 2ND 042 | C112: 200 | D112: Membership (EFT) | E112: MATCHED | F112: HIGH | G112: Robert | H112: 138 | I112: Second Ave.
A113: 25/05/2026 | B113: SN MESSENGER | C113: 300 | D113: Membership (EFT) | E113: MATCHED | F113: HIGH | G113: Steve Messenger/Juanita | H113: 128 | I113: First Avenue
...

Sheet Expense Register
A1: Date | B1: Reference (bank) | C1: Category | D1: Amount (R) | E1: Notes
A2: 02/03/2026 | B2: CAPITEC B MCA1 03-26 | C2: Bank fee | D2: 414.98 | E2: DO service charge
A3: 04/03/2026 | B3: JLK MCAA | C3: Expense | D3: 4000 | E3: JLK MCAA
A4: 04/03/2026 | B4: MR SN LANGA MCAA Water | C4: Utilities | D4: 471.51 | E4: Water — MR SN LANGA
A5: 04/03/2026 | B5: 001 UNPAIDS/WEIERINGS CAPITEC | C5: Reversal | D5: 200 | E5: Unpaid DO reversal
A6: 27/03/2026 | B6: Mengo Sibanda MCAA | C6: Salary | D6: 12500 | E6: Monthly salary — Mengo Sibanda
A7: 27/03/2026 | B7: LUKA MCAA FENCE | C7: Maintenance | D7: 3834 | E7: Fence repair — Luka
A8: 28/03/2026 | B8: 001 UNPAIDS/WEIERINGS DISC | C8: Reversal | D8: 350 | E8: Unpaid DO reversal
A9: 29/03/2026 | B9: MR SN LANGA MCAA Water | C9: Utilities | D9: 471.51 | E9: Water — MR SN LANGA
A10: 30/03/2026 | B10: TARY DESIGN MCAA | C10: Camera purchase | D10: 14500 | E10: Camera equipment — Tary Design
A11: 31/03/2026 | B11: Month S/Fee | C11: Bank fee | D11: 50 | E11: Monthly account fee
C12: MARCH 2026 TOTAL | D12: 36792
A13: April 2026
A14: 01/04/2026 | B14: CAPITEC B MCA1 04-26 | C14: Bank fee | D14: 440.61 | E14: DO service charge
A15: 02/04/2026 | B15: Red Hot Bit Consultants MCAA | C15: Other | D15: 3458 | E15: Unclassified outgoing — verify with admin
A16: 14/04/2026 | B16: TARY DESIGN MCAA | C16: Camera purchase | D16: 14502 | E16: Camera equipment — Tary Design
A17: 16/04/2026 | B17: 001 UNPAIDS/WEIERINGS CAPITEC | C17: Reversal | D17: 170 | E17: Unpaid DO reversal — R170
A18: 27/04/2026 | B18: Mengo Sibanda MCAA | C18: Salary | D18: 12506 | E18: Monthly salary — Mengo Sibanda
A19: 27/04/2026 | B19: LUKA MCAA FENCE | C19: Maintenance | D19: 4756 | E19: Fence repair — Luka
A20: 29/04/2026 | B20: 001 UNPAIDS/WEIERINGS DISC | C20: Reversal | D20: 350 | E20: Unpaid DO reversal — R350
A21: 30/04/2026 | B21: Month S/Fee | C21: Bank fee | D21: 50 | E21: Monthly account fee
C22: APRIL 2026 TOTAL | D22: 36232.61
A23: May 2026
A24: 02/05/2026 | B24: MR SN LANGA MCAA Water | C24: Utilities | D24: 574 | E24: Water/utilities – MR SN Langa. Incl R1 fee.
A25: 04/05/2026 | B25: CAPITEC B MCA1 05-26 | C25: Bank fee | D25: 462.45 | E25: DO service charge – Capitec
A26: 04/05/2026 | B26: 001 UNPAIDS/WEIERINGS STANDARD | C26: Reversal | D26: 350 | E26: Unpaid DO reversal – R350 (member unknown, bounced at Standard Bank)
A27: 09/05/2026 | B27: TARY DESIGN MCAA | C27: Camera purchase | D27: 16820.06 | E27: Camera equipment – Tary Design. Incl R2 fee.
A28: 09/05/2026 | B28: Reimbursement Nel St Camera refund | C28: Camera refund | D28: 502 | E28: Nel Street camera refund payment. Incl R2 fee.
A29: 16/05/2026 | B29: 001 UNPAIDS/WEIERINGS CAPITEC | C29: Reversal | D29: 170 | E29: EFT reversal – G. van Jaarsveld (87 Golf Course) – Capitec reject
A30: 25/05/2026 | B30: LUKA MCAA FENCE | C30: Maintenance | D30: 4752 | E30: Fence repair – Luka. Incl R2 fee.
A31: 25/05/2026 | B31: Mengo Sibanda MCAA | C31: Salary | D31: 12502 | E31: Monthly salary – Mengo Sibanda. Incl R2 fee.
A32: 29/05/2026 | B32: ATM fees (54 Nico Pelser + NEL ST ANDREW) | C32: Bank fee | D32: 29.54 | E32: ATM cash deposit fees: R22.40 + R7.14
A33: 31/05/2026 | B33: Month S/Fee | C33: Bank fee | D33: 50 | E33: Monthly account fee
C34: MAY 2026 TOTAL | D34: 36212.05
C35: GRAND TOTAL (Mar + Apr + May) | D35: 109236.66

Sheet Payment Summary
B2: MCAA MEMBERSHIP — PAYMENT OVERVIEW
B3: Mar 2025 – May 2026 | Comprehensive List Analysis
B5: MEMBERSHIP SNAPSHOT
B7: Total entries on list | D7: 533
B8: Paying members | D8: 132
B9: Non-paying members | D9: 401
B11: Unique plot numbers | D11: 184
B12: Plots with multiple entries | D12: 118
B14: Total revenue collected (R) | D14: 372684
B16: Payment Rate | D16: 0.25
B17: 401 members have made no payments this year.
B19: MONTHLY COLLECTIONS
B21: Month | C21: Total Collected (R) | D21: # Payers
B22: 46106 | C22: 26778 | D22: 79
B23: 46137 | C23: 25841 | D23: 78
B24: 46167 | C24: 25108 | D24: 74
B25: 46198 | C25: 24028 | D25: 70
B26: 46228 | C26: 30233 | D26: 71
B27: 46259 | C27: 26733 | D27: 68
B28: 46290 | C28: 24183 | D28: 70
B29: 46320 | C29: 21583 | D29: 64
B30: 46351 | C30: 22883 | D30: 66
B31: 46381 | C31: 24233 | D31: 69
B32: 46048 | C32: 32833 | D32: 66
B33: 46079 | C33: 27373 | D33: 75
... B36: 46168 | C36: 29945 | D36: 79
B37: TOTAL

Sheet Members Report
A1: MCAA — MEMBERS PAYMENT DETAIL REPORT
A2: Mar 2025 – Apr 2026 | Rows highlighted in red = zero payments recorded this year
A4: ✅ PAYING MEMBERS
A5: Owner / Tenant | B5: Street / Address | C5: Plot | D5: Total Paid (R) | E5: Source (D/O or EFT)
A6: Paul Gronebaum | B6: Ohenimuri | C6: 8 | D6: 4550
A7: Jason Batalides | B7: Blignaut Street | C7: 1 | D7: 4550
A8: Ian Long | B8: Blignaut Street | C8: 10 | D8: 4550
A9: John Carr | B9: Blignaut Street | C9: 11 | D9: 3500
A10: Evelyn Keartland | B10: De Wet Street | C10: 91 | D10: 5050
A11: Richard & Susan Bentheim | B11: De Wet Street | C11: 93 | D11: 4719
A12: Paul & Liz Lottreaux (Celtic Software) | B12: De Wet Street | C12: 101 | D12: 4550
A13: Aaqil Pariachi | B13: De Wet Street | C13: 104 | D13: 350
A14: Nazam | B14: De Wet Street | C14: 108 | D14: 850
A15: Sifiso Masango / Tumiso | B15: De Wet Street | C15: 110 | D15: 1000
A16: Phil & Chanty Gomes | B16: De Wet Street | C16: 116 | D16: 3600
A17: Rachel Balthazar | B17: Road No 8 | C17: 143 | D17: 1200
... A35: Janos Herceg | B35: Centre Road | C35: 51 | D35: 4550
A36: Millicent Nkosi | B36: Centre Road | C36: 54-1 | D36: 200
A37: No reference | B37: Fifth Street | C37: ? | D37: 500
A38: Pieter Fourie | B38: Fifth Street | C38: 19 | D38: 5550
A39: Andrew & Robyn Weeks | B39: Fifth Street | C39: 20 | D39: 4550
A40: Alan & Louise Proudfoot | B40: Fifth Street | C40: 25 | D40: 5005
A41: Eschelle Wathen | B41: Fifth Street | C41: 53 | D41: 4550
A42: Cindy Wills | B42: Fifth Street | C42: 59 | D42: 5720
A43: Basil | B43: Fifth Street | C43: 61 | D43: 6750
A44: Miroslaw Benpkavic | B44: Danie Theron | C44: 9 | D44: 15500
A45: Heinrich Hendrikz | B45: Danie Theron | C45: 10 | D45: 500
A46: Andre Brummer | B46: Danie Theron | C46: 81 | D46: 3000
A47: Terry Shapiro | B47: Danie Theron | C47: 82 | D47: 5050
A48: Thulani Timile | B48: Danie Theron | C48: 117 | D48: 1200
A49: Gerald Bezuidenhout (Fuel Trailers) | B49: First Avenue | C49: 1,3,7 | D49: 350
A50: Lesley Visser | B50: First Avenue | C50: 9 | D50: 4550
A51: Abbeyfield | B51: First Avenue | C51: 16 | D51: 4550
A52: Wayne Pettit | B52: First Avenue | C52: 17 | D52: 4719
A53: Carien Abrahams | B53: First Avenue | C53: 22 | D53: 4550
A54: May Lyna/ Judith | B54: First Avenue | C54: 25 | D54: 1050
A55: Peter Kairuz | B55: First Avenue | C55: 37 | D55: 5050
A56: Jose Pinto | B56: First Avenue | C56: 39 | D56: 4550
A57: Steve Messenger/Juanita | B57: First Avenue | C57: 41 | D57: 4000
A58: Shaun Traut | B58: First Avenue | C58: 43 | D58: 5050
A59: Ratheo Molebatsi | B59: First Avenue | C59: 49 | D59: 2450
A60: Bruce Magill | B60: First Avenue | C60: 49 | D60: 700
A61: Hazel Titterton | B61: First Avenue | C61: 115 | D61: 4719
... A87: Stacey Ireland | B87: Hillside Road | C87: 59 | D87: 170
A88: Gadatia Mustak | B88: Hillside Road | C88: 69/71 | D88: 3900
A89: Sayed Zainulabidien | B89: Hillside Road | C89: 73 | D89: 4550
A90: Sandile Mbanjwa | B90: Hugenote Street | C90: 22 | D90: 4200
A91: Philip Kruis | B91: Nel Street | C91: 70 | D91: 1000
A92: Nathaniel Ramsden | B92: Nel Street | C92: 78 | D92: 2500
A93: A Kennelly | B93: Nel Street | C93: 80 | D93: 83
A94: Graham Thiele | B94: Nel Street | C94: 83 | D94: 1670
A95: Gale Webb (Montage Agencies) | B95: Nel Street | C95: 86 | D95: 3900
A96: K Bland | B96: Nel Street | C96: 88 | D96: 500
A97: Bheki & Nthabiseng Malinga | B97: Nel Street | C97: 88b | D97: 4550
A98: Tracey Van Niekerk | B98: Nel Street | C98: 90 | D98: 4550
A99: Isobel Van Der Motten | B99: Nel Street | C99: 92 | D99: 500
A100: Debbie Rautenbach (Liesl Seymore) | B100: Nel Street | C100: 94 | D100: 4400
A101: Andrew Chapman | B101: Nel Street | C101: 96 | D101: 1000
A102: Mbulelo Mbenenge | B102: Nel Street | C102: 100 | D102: 500
A103: Perfect Zama Ndlovu (Security) | B103: Nico Pelser | C103: 48 | D103: 1000
A104: Chris and Bernadette Momple | B104: Nico Pelser | C104: 50 | D104: 2040
A105: Richard and Pumla Mashele | B105: Nico Pelser | C105: 54 | D105: 900
A106: Nozisi (Nono) Sibeko & Given Sibeko | B106: Nico Pelser | C106: 58 | D106: 300
A107: Peggy Bennett | B107: Nico Pelser | C107: 62 | D107: 5700
A108: Reginald Kairuz and Lucielle De Klerk | B108: Nico Pelser | C108: 65 | D108: 6220
A109: Bradley and Sharon Bantjes | B109: Nico Pelser | C109: 66 | D109: 5700
... A118: Rob Roos | B118: Second Ave. | C118: 42 | D118: 2600
A119: Donovan and Karen Mateman | B119: Road No 7 (No Name) | C119: 148/0 | D119: 350
A120: Johan and Lelly De Vries (Tennants) | B120: Road No 7 (No Name) | C120: 148/1 | D120: 2200
A121: Hendrik Strydom | B121: Road No 7 | C121: 150 | D121: 350
A122: Henry and Catarina Moorcroft | B122: Road No 7 | C122: 151 | D122: 3850
A123: HES Moorcraft | B123: Road No 7 | C123: 151 | D123: 3500
A124: Zama and Petunia Hlongwane | B124: Road No 7 | C124: 153 | D124: 4200
A125: Venessa Venter | B125: Road No 7 | C125: 243 | D125: 170
A126: Gideon and Antonette de Beer | B126: Road No 7 | C126: 243/1 | D126: 4550
A127: Andre De Vries | B127: Road No 7 | C127: 244 | D127: 690
A128: Rudolf & Susanna Seifert | B128: Road No 7 | C128: 245 | D128: 4550
A129: Leonard and Faith Manqalaza | B129: Road No 7 | C129: 247 | D129: 1750
A130: Gift & Charity Muthala | B130: Road No 7 | C130: 248/1 | D130: 580
A131: Getruida (Ida) Vermaak | B131: Road No 7 | C131: 249/1 | D131: 3900
A132: Petrus Johannes Potgieter (Ronnie) | B132: Short Road | C132: 77 | D132: 340
A133: Damaskus Projects | B133: - | D133: 500
A134: Fifth Street | B134: - | D134: 1000
A135: Van Niekerk | B135: - | D135: 600
A136: Byron Nel Street | B136: - | D136: 500
A137: BlgN15F | B137: - | D137: 500
A138: TOTAL PAYING
A140: ❌ NON-PAYING MEMBERS
A141: Owner / Tenant | B141: Street / Address | C141: Plot | D141: Status | E141: D/O Ref
A142: Nomvula Shelembe | B142: Ohenimuri | C142: 7 | D142: No payment recorded
A143: Ramushu - Catholic Church | B143: Angle Road | C143: 39 | D143: No payment recorded
A144: Clinton Fortuin | B144: Angle Road | C144: 48 | D144: No payment recorded
A145: Darren Booysen | B145: Angle Road | C145: 48 | D145: No payment recorded
A146: Mtshali Nhlanhla | B146: Angle Road | C146: 188? | D146: No payment recorded
A147: Desire (Girls on the Move) | B147: Blignaut Street | C147: 8 | D147: No payment recorded
A148: Anthony Byrne | B148: Blignaut Street | C148: 8a | D148: No payment recorded
A149: Nkosinomusa Mpanza | B149: Blignaut Street | C149: 12 | D149: No payment recorded
A150: Colin Blandford | B150: Blignaut Street | C150: 14 | D150: No payment recorded
A151: Patrick Mudhara | B151: Blignaut Street | C151: 14 | D151: No payment recorded
A152: R Baloi | B152: De Wet Street | C152: ? | D152: No payment recorded
...

Sheet Street Captains
A1: MCAA Street Captains
A2: Blignaut Street | E2: 4 of 8
A3: De Wet Street | B3: Richard Bentheim | C3: richieinza@gmail.com | D3: 084 304 1478 | E3: 7 of 17
A4: Eloff Street | E4: 7 of 19
A5: Road No 8 | E5: 1 of 5
A6: Eufees Street | B6: Rolf | C6: rolfhanswillenbrock@gmail.com | D6: 083 463 6402 | E6: 2 of 11
A7: Fifth Street | B7: Thulani Timile | C7: sabdmc@mail.com | D7: 083 959 2854 | E7: 5 of 21
A8: First Avenue | E8: 9 of 30
A9: Golf Course Road | B9: Kevin | C9: kevin@camerapress.co.za | D9: 082 490 8066 | E9: 9 of 26
A10: Green/Angle Road | B10: Mark Thompson | C10: markthompson.mt941@gmail.com | D10: 083 260 9080 | E10: 4 of 14
A11: Hillside Road | B11: James Owens | C11: Jamesaowens@gmail.com | D11: 0836557792 | E11: 5 of 27
A12: Hugenote Street | E12: 0 of 12
A13: Nel Street | B13: Cliff Webb | C13: cliff@paradigmprint.co.za | D13: 082 571 5142 | E13: 4 of 16
A14: Nico Pelser/Fourth St. | B14: Paul Lottreaux | C14: Lottreauxpaul@gmail.com | D14: 081 098 3664 | E14: 3 of 26
A15: Orchard Road | B15: Anton | C15: anton@abceramics.co.za | D15: 078 925 3151 | E15: 1 of 19
A16: Third Ave. | B16: Chris Leeson | C16: Chris@cai.co.za | D16: 083 600 0450 | E16: 1 of 14
A17: Second Avenue | E17: 2 of 18
A18: Road No 7 | B18: Zama Hlongwane | C18: zamohr@gmail.com | D18: 083 265 1152 | E18: 3 of 17
A19: Voortrekker Street | E19: 1 of 13

Sheet Blignautsrus North
A1: Owner / Tenant | B1: Address | C1: D/O Ref | D1: Plot | E1: Contact 1 | F1: Contact 2 | G1: Contact 3 | H1: E-mail address | I1: Comments Sep | J1: Jan-25 DO | K1: Jan-25 EFT | L1: Feb-25 DO | M1: Feb-25 EFT | N1: Mar-25 DO | O1: Mar-25 EFT | P1: Apr-25 DO | Q1: Apr-25 EFT | R1: May-25 DO | S1: May-25 EFT | T1: Jun-25 DO | U1: Jun-25 EFT | V1: Jul-25 DO | W1: Jul-25 EFT | X1: Aug-25 DO | Y1: Aug-25 EFT | Z1: Sep-25 DO | AA1: Sep-25 EFT | AB1: Oct-25 DO | AC1: Oct-25 EFT | AD1: Nov-25 DO | AE1: Nov-25 EFT | AF1: Dec-25 DO | AG1: Dec-25 EFT | AH1: Jan-26 DO | AI1: Jan-26 EFT | AJ1: Feb-26 DO | AK1: Feb-26 EFT | AL1: Mar-26 DO | AM1: Mar-26 EFT | AN1: Comments
A2: Jason Batalides | B2: Blignaut Street | C2: HZB038 | D2: 1 | E2: 082 557 1110 | F2: 0614960119 | J2: 350 | L2: 350 | N2: 350 | P2: 350 | R2: 350 | T2: 350 | V2: 350 | X2: 350 | Z2: 350 | AB2: 350 | AD2: 350 | AF2: 350 | AH2: 350 | AJ2: 350 | AL2: 350 | AN2: HZB038 = D/O ref
B3: Blignaut Street | D3: 4
B4: Blignaut Street | D4: 6
A5: Desire (Girls on the Move) | B5: Blignaut Street | D5: 8 | AN5: Wants to start paying end Jan
A6: Anthony Byrne | B6: Blignaut Street | C6: BLG08A | D6: 8a
A7: Ian Long | B7: Blignaut Street | C7: BLG010 | D7: 10 | J7: 350 | L7: 350 | N7: 350 | P7: 350 | R7: 350 | T7: 350 | V7: 350 | X7: 350 | Z7: 350 | AB7: 350 | AD7: 350 | AF7: 350 | AH7: 350 | AJ7: 350 | AL7: 350
A8: John Carr | B8: Blignaut Street | C8: EFT | D8: 11 | W8: 700 | Y8: 350 | AA8: 350 | AC8: 350 | AE8: 350 | AG8: 350 | AI8: 350 | AK8: 350 | AM8: 350 | AN8: New Jul25
B9: Blignaut Street | D9: 12
A10: Colin Blandford | B10: Blignaut Street | C10: BLG14 | D10: 14
B11: Blignaut Street | D11: 16
A14: Greg Stevens | B14: Eeufees Street | D14: 3 | E14: 082 466 6457
A17: Gerald Bezuidenhout (Fuel Trailers) | B17: First Avenue | C17: 1ST001 | D17: 1 | E17: 011 730 8031
A18: Lesley Visser | B18: First Avenue | C18: 1ST009 | D18: 9b | E18: 083 469 7838 | H18: midvaalward7@gmail.com | J18: 350 | L18: 350 | N18: 350 | P18: 350 | R18: 350 | T18: 350 | V18: 350 | X18: 350 | Z18: 350 | AB18: 350 | AD18: 350 | AF18: 350 | AH18: 350 | AJ18: 350 | AL18: 350
B19: First Avenue | D19: 11
B20: First Avenue | D20: 13
A21: Alistair Leukes | B21: First Avenue | D21: 15 | E21: 061 467 8440 | H21: alistair@amlsol.com
A22: Abbeyfield | B22: First Avenue | C22: BLG 016 | D22: 16 | J22: 350 | L22: 350 | N22: 350 | P22: 350 | R22: 350 | T22: 350 | V22: 350 | X22: 350 | Z22: 350 | AB22: 350 | AD22: 350 | AF22: 350 | AH22: 350 | AJ22: 350 | AL22: 350
A23: Wayne Pettit | B23: First Avenue | C23: BLG 017 | D23: 17 | J23: 363 | L23: 363 | N23: 363 | P23: 363 | R23: 363 | T23: 363 | V23: 363 | X23: 363 | Z23: 363 | AB23: 363 | AD23: 363 | AF23: 363 | AH23: 363 | AJ23: 363 | AL23: 363
B26: Hugenote Street | D26: 3
B27: Hugenote Street | D27: 5
A28: Eugene | B28: Hugenote Street | D28: 7 | E28: 076 440 9248
B29: Hugenote Street | D29: 9
A30: Adams | B30: Hugenote Street | D30: 11 | E30: 072 908 9502
A31: Fanie | B31: Hugenote Street | D31: 13 | E31: 063 088 3257 | H31: fanie@kieda.co.za
A32: Ncedo Vilikati | B32: Hugenote Street | D32: 15 | E32: 079 707 1993
B33: Hugenote Street | D33: 17
A34: Karel | B34: Hugenote Street | D34: 18 | E34: 082 308 1525 | H34: karel@kfb.co.za
A35: Minnie | B35: Hugenote Street | D35: 20 | E35: 082 796 7074 | H35: tinus@kwn.co.za
A36: Sandile Mbanjwa | B36: Hugenote Street | D36: 22 | AI36: 4200 | AN36: Annual payment 16/01/26
A37: K. Aboobaker | B37: Hugenote Street | D37: 24 | E37: 081 385 5048 | H37: mentorconch11@gmail.com
B40: Voortrekker St. | D40: 19
B41: Voortrekker St. | D41: 21
B42: Voortrekker St. | D42: 23
B43: Voortrekker St. | D43: 25
B44: Voortrekker St. | D44: 26
B45: Voortrekker St. | D45: 27
B46: Voortrekker St. | D46: 29
B47: Voortrekker St. | D47: 31
B48: Voortrekker St. | D48: 35
B49: Voortrekker St. | D49: 37
B50: Voortrekker St. | D50: 39
B51: Voortrekker St. | D51: 41
J52: =SUM(J2:J51) -> 1763 | K52: =SUM(K2:K51) -> 0 | L52: =SUM(L2:L51) -> 1763 | M52: =SUM(M2:M51) -> 0 | N52: =SUM(N2:N51) -> 1763 | O52: =SUM(O2:O51) -> 0 | P52: =SUM(P2:P51) -> 1763 | Q52: =SUM(Q2:Q51) -> 0 | ... AM52: =SUM(AM2:AM51) -> 350
J54: Bal b/fwd | K54: 0 | L54: Bal b/fwd | M54: =K61 -> 1763 | N54: Bal b/fwd | O54: =M61 -> 3526 | P54: Bal b/fwd | Q54: =O61 -> 5289 | R54: Bal b/fwd | S54: =Q61 -> 7052 | T54: Bal b/fwd | U54: =S61 -> 8815 | V54: Bal b/fwd | W54: =U61 -> 0 | X54: Bal b/fwd | Y54: =W61 -> 2463 | Z54: Bal b/fwd | AA54: =Y61 -> 4576 | AB54: Bal b/fwd | AC54: =AA61 -> 6689 | AD54: Bal b/fwd | AE54: =AC61 -> 5440.4 | AF54: Bal B/fwd | AG54: =AE61 -> 7553.4 | AH54: Bal B/fwd | AI54: 9666.4 | AK54: =AI61 -> 14871.8 | AM54: 16984.8
J55: Add D/Orders | K55: =J52 -> 1763 | L55: Add D/Orders | M55: =L52 -> 1763 | N55: Add D/Orders | O55: =N52 -> 1763 | P55: Add D/Orders | Q55: =P52 -> 1763 | R55: Add D/Orders | S55: =R52 -> 1763 | T55: Add D/Orders | U55: =T52 -> 1763 | V55: Add D/Orders | W55: =V52 -> 1763 | X55: Add D/Orders | Y55: =X52 -> 1763 | Z55: Add D/Orders | AA55: =Z52 -> 1763 | AB55: Add D/Orders | AC55: =AA55 -> 1763 | AD55: Add D/Orders | AE55: =AD52 -> 1763 | AF55: Add D/Orders | AG55: =AF52 -> 1763 | AH55: Add D/Orders | AI55: =AH52 -> 1763 | AJ55: Add D/Orders | AK55: =AJ52 -> 1763 | AL55: Add D/Orders | AM55: =AL52 -> 1763
J56: Add EFTs | K56: =K52 -> 0 | L56: Add EFTs | M56: =M52 -> 0 | N56: Add EFTs | O56: =O52 -> 0 | P56: Add EFTs | Q56: =Q52 -> 0 | R56: Add EFTs | S56: =S52 -> 0 | T56: Add EFTs | U56: =U52 -> 0 | V56: Add EFTs | W56: =W52 -> 700 | X56: Add EFTs | Y56: =Y52 -> 350 | Z56: Add EFTs | AA56: =AA52 -> 350 | AB56: Add EFTs | AC56: =AA56 -> 350 | AD56: Add EFTs | AE56: =AE52 -> 350 | AF56: Add EFTs | AG56: =AG52 -> 350 | AH56: Add EFTs | AI56: =AI52 -> 4550 | AJ56: Add EFTs | AK56: =AK52 -> 350 | AL56: Add EFTs | AM56: =AM52 -> 350
T57: 1st Ave gate contribution | U57: -9550 | AB57: 10/10 Saxmoore for Bnorth | AC57: -2254 | AH57: Luka work | AI57: -1107.6
T58: Luka work | U58: -1028 | AB58: Luka work | AC58: -1107.6
J61: Bal 31/1 | K61: =SUM(K54:K60) -> 1763 | L61: Bal 28/2 | M61: =SUM(M54:M60) -> 3526 | N61: Bal 31/3 | O61: =SUM(O54:O60) -> 5289 | P61: Bal 30/4 | Q61: =SUM(Q54:Q60) -> 7052 | R61: Bal 31/5 | S61: =SUM(S54:S60) -> 8815 | T61: Bal 30/6 | U61: =SUM(U54:U60) -> 0 | V61: Bal 31/7 | W61: =SUM(W54:W60) -> 2463 | X61: Bal 31/8 | Y61: =SUM(Y54:Y60) -> 4576 | Z61: Bal 30/9 | AA61: =SUM(AA54:AA60) -> 6689 | AB61: Bal 31/10 | AC61: =SUM(AC54:AC60) -> 5440.4 | AD61: Bal 30/11 | AE61: =SUM(AE54:AE60) -> 7553.4 | AF61: Bal 31/12 | AG61: =SUM(AG54:AG60) -> 9666.4 | AH61: Bal 31/1 | AI61: =SUM(AI54:AI60) -> 14871.8 | AJ61: Bal 28/2 | AK61: =SUM(AK54:AK60) -> 16984.8 | AL61: Bal 31/3 | AM61: =SUM(AM54:AM60) -> 19097.8

Sheet Notes
A1: Sample of how to load on old Mercantile system - see below snip | I1: Capitec supp | J1: 021 137 6818
A2: Print financial reports which has all info including unpaid debit orders for recon
A3: User Paul - MCA1 - Sharon**9
A5: https://ebureau.mercantile.co.za/meb3/online/
